<uav.map.converter.map.Map>
  <regions>
    <uav.map.converter.map.Poly2D>
      <nameRegion>0</nameRegion>
      <typeRegion>NFZ_REGION</typeRegion>
      <coordenates>
        <uav.map.converter.map.Point2D>
          <x>-18.708909921595755</x>
          <y>107.98903510492447</y>
        </uav.map.converter.map.Point2D>
        <uav.map.converter.map.Point2D>
          <x>12.762102143039352</x>
          <y>79.94459244570635</y>
        </uav.map.converter.map.Point2D>
        <uav.map.converter.map.Point2D>
          <x>20.390406286877443</x>
          <y>58.26775639424577</y>
        </uav.map.converter.map.Point2D>
        <uav.map.converter.map.Point2D>
          <x>-23.841394092209118</x>
          <y>46.52979098601046</y>
        </uav.map.converter.map.Point2D>
        <uav.map.converter.map.Point2D>
          <x>-39.63198408288307</x>
          <y>64.26701953659844</y>
        </uav.map.converter.map.Point2D>
      </coordenates>
    </uav.map.converter.map.Poly2D>
    <uav.map.converter.map.Poly2D>
      <nameRegion>1</nameRegion>
      <typeRegion>NFZ_REGION</typeRegion>
      <coordenates>
        <uav.map.converter.map.Point2D>
          <x>-105.10451927695651</x>
          <y>117.4066469211655</y>
        </uav.map.converter.map.Point2D>
        <uav.map.converter.map.Point2D>
          <x>-83.41982281482906</x>
          <y>128.26798634827256</y>
        </uav.map.converter.map.Point2D>
        <uav.map.converter.map.Point2D>
          <x>-68.32285470214924</x>
          <y>109.98323438586655</y>
        </uav.map.converter.map.Point2D>
        <uav.map.converter.map.Point2D>
          <x>-77.22046722561286</x>
          <y>87.29665297611639</y>
        </uav.map.converter.map.Point2D>
        <uav.map.converter.map.Point2D>
          <x>-101.63139941130751</x>
          <y>91.50387385602713</y>
        </uav.map.converter.map.Point2D>
      </coordenates>
    </uav.map.converter.map.Poly2D>
    <uav.map.converter.map.Poly2D>
      <nameRegion>0</nameRegion>
      <typeRegion>PENALTY_REGION</typeRegion>
      <coordenates>
        <uav.map.converter.map.Point2D>
          <x>-171.57328223564343</x>
          <y>8.489326065678</y>
        </uav.map.converter.map.Point2D>
        <uav.map.converter.map.Point2D>
          <x>-415.63724468872914</x>
          <y>110.06200745951129</y>
        </uav.map.converter.map.Point2D>
        <uav.map.converter.map.Point2D>
          <x>-236.2050664419867</x>
          <y>569.9502597107227</y>
        </uav.map.converter.map.Point2D>
        <uav.map.converter.map.Point2D>
          <x>20.6574010206816</x>
          <y>456.4334107343441</y>
        </uav.map.converter.map.Point2D>
      </coordenates>
    </uav.map.converter.map.Poly2D>
    <uav.map.converter.map.Poly2D>
      <nameRegion>1</nameRegion>
      <typeRegion>PENALTY_REGION</typeRegion>
      <coordenates>
        <uav.map.converter.map.Point2D>
          <x>95.15502170371037</x>
          <y>-116.89782430777612</y>
        </uav.map.converter.map.Point2D>
        <uav.map.converter.map.Point2D>
          <x>66.34792415346973</x>
          <y>-205.23365043747012</y>
        </uav.map.converter.map.Point2D>
        <uav.map.converter.map.Point2D>
          <x>-147.37038496801375</x>
          <y>-113.48336930933246</y>
        </uav.map.converter.map.Point2D>
        <uav.map.converter.map.Point2D>
          <x>-112.65460164628492</x>
          <y>-28.661852393453234</y>
        </uav.map.converter.map.Point2D>
      </coordenates>
    </uav.map.converter.map.Poly2D>
    <uav.map.converter.map.Poly2D>
      <nameRegion>2</nameRegion>
      <typeRegion>PENALTY_REGION</typeRegion>
      <coordenates>
        <uav.map.converter.map.Point2D>
          <x>202.82475158239217</x>
          <y>373.5027178769953</y>
        </uav.map.converter.map.Point2D>
        <uav.map.converter.map.Point2D>
          <x>128.3456455967095</x>
          <y>50.558335216067434</y>
        </uav.map.converter.map.Point2D>
        <uav.map.converter.map.Point2D>
          <x>-104.98402732353111</x>
          <y>153.06426337065352</y>
        </uav.map.converter.map.Point2D>
        <uav.map.converter.map.Point2D>
          <x>23.800576346598127</x>
          <y>454.5877127526458</y>
        </uav.map.converter.map.Point2D>
      </coordenates>
    </uav.map.converter.map.Poly2D>
    <uav.map.converter.map.Poly2D>
      <nameRegion>0</nameRegion>
      <typeRegion>BONUS_REGION</typeRegion>
      <coordenates>
        <uav.map.converter.map.Point2D>
          <x>107.57680489679771</x>
          <y>12.994428663285342</y>
        </uav.map.converter.map.Point2D>
        <uav.map.converter.map.Point2D>
          <x>110.91440435432467</x>
          <y>0.5331237155303437</y>
        </uav.map.converter.map.Point2D>
        <uav.map.converter.map.Point2D>
          <x>-77.49714640274891</x>
          <y>-26.79301341999265</y>
        </uav.map.converter.map.Point2D>
        <uav.map.converter.map.Point2D>
          <x>-140.95705262643762</x>
          <y>5.585120886752694</y>
        </uav.map.converter.map.Point2D>
      </coordenates>
    </uav.map.converter.map.Poly2D>
    <uav.map.converter.map.Poly2D>
      <nameRegion>1</nameRegion>
      <typeRegion>BONUS_REGION</typeRegion>
      <coordenates>
        <uav.map.converter.map.Point2D>
          <x>-68.182797773551</x>
          <y>58.068542699893975</y>
        </uav.map.converter.map.Point2D>
        <uav.map.converter.map.Point2D>
          <x>-61.789727917114256</x>
          <y>32.391834372181094</y>
        </uav.map.converter.map.Point2D>
        <uav.map.converter.map.Point2D>
          <x>-133.48405301203252</x>
          <y>28.8397996834276</y>
        </uav.map.converter.map.Point2D>
        <uav.map.converter.map.Point2D>
          <x>-131.14163716862265</x>
          <y>53.93663406243162</y>
        </uav.map.converter.map.Point2D>
        <uav.map.converter.map.Point2D>
          <x>-117.22558997838834</x>
          <y>76.03457494705266</y>
        </uav.map.converter.map.Point2D>
      </coordenates>
    </uav.map.converter.map.Poly2D>
    <uav.map.converter.map.Poly2D>
      <nameRegion>2</nameRegion>
      <typeRegion>BONUS_REGION</typeRegion>
      <coordenates>
        <uav.map.converter.map.Point2D>
          <x>6.712931072653281</x>
          <y>-30.213680595576523</y>
        </uav.map.converter.map.Point2D>
        <uav.map.converter.map.Point2D>
          <x>47.91681230882898</x>
          <y>-23.59608649500882</y>
        </uav.map.converter.map.Point2D>
        <uav.map.converter.map.Point2D>
          <x>51.26490269414791</x>
          <y>-52.9418146611102</y>
        </uav.map.converter.map.Point2D>
        <uav.map.converter.map.Point2D>
          <x>5.894124631912962</x>
          <y>-56.27856970995165</y>
        </uav.map.converter.map.Point2D>
        <uav.map.converter.map.Point2D>
          <x>-20.439072174400952</x>
          <y>-41.32415481274299</y>
        </uav.map.converter.map.Point2D>
      </coordenates>
    </uav.map.converter.map.Poly2D>
  </regions>
</uav.map.converter.map.Map>