<uav.map.converter.map.Map>
  <regions>
    <uav.map.converter.map.Poly2D>
      <nameRegion>0</nameRegion>
      <typeRegion>NFZ_REGION</typeRegion>
      <coordenates>
        <uav.map.converter.map.Point2D>
          <x>286.23</x>
          <y>-557.89</y>
        </uav.map.converter.map.Point2D>
        <uav.map.converter.map.Point2D>
          <x>76.31</x>
          <y>-545.7</y>
        </uav.map.converter.map.Point2D>
        <uav.map.converter.map.Point2D>
          <x>88.49</x>
          <y>-335.78</y>
        </uav.map.converter.map.Point2D>
        <uav.map.converter.map.Point2D>
          <x>298.41</x>
          <y>-347.97</y>
        </uav.map.converter.map.Point2D>
      </coordenates>
    </uav.map.converter.map.Poly2D>
    <uav.map.converter.map.Poly2D>
      <nameRegion>1</nameRegion>
      <typeRegion>NFZ_REGION</typeRegion>
      <coordenates>
        <uav.map.converter.map.Point2D>
          <x>-205.17</x>
          <y>-67.19</y>
        </uav.map.converter.map.Point2D>
        <uav.map.converter.map.Point2D>
          <x>-353.64</x>
          <y>-148.58</y>
        </uav.map.converter.map.Point2D>
        <uav.map.converter.map.Point2D>
          <x>-435.04</x>
          <y>-0.11</y>
        </uav.map.converter.map.Point2D>
        <uav.map.converter.map.Point2D>
          <x>-286.56</x>
          <y>81.27</y>
        </uav.map.converter.map.Point2D>
      </coordenates>
    </uav.map.converter.map.Poly2D>
    <uav.map.converter.map.Poly2D>
      <nameRegion>2</nameRegion>
      <typeRegion>NFZ_REGION</typeRegion>
      <coordenates>
        <uav.map.converter.map.Point2D>
          <x>-368.14</x>
          <y>211.14</y>
        </uav.map.converter.map.Point2D>
        <uav.map.converter.map.Point2D>
          <x>-388.86</x>
          <y>40.35</y>
        </uav.map.converter.map.Point2D>
        <uav.map.converter.map.Point2D>
          <x>-559.65</x>
          <y>61.07</y>
        </uav.map.converter.map.Point2D>
        <uav.map.converter.map.Point2D>
          <x>-538.93</x>
          <y>231.86</y>
        </uav.map.converter.map.Point2D>
      </coordenates>
    </uav.map.converter.map.Poly2D>
    <uav.map.converter.map.Poly2D>
      <nameRegion>3</nameRegion>
      <typeRegion>NFZ_REGION</typeRegion>
      <coordenates>
        <uav.map.converter.map.Point2D>
          <x>381.52</x>
          <y>174.84</y>
        </uav.map.converter.map.Point2D>
        <uav.map.converter.map.Point2D>
          <x>259.27</x>
          <y>245.34</y>
        </uav.map.converter.map.Point2D>
        <uav.map.converter.map.Point2D>
          <x>329.78</x>
          <y>367.59</y>
        </uav.map.converter.map.Point2D>
        <uav.map.converter.map.Point2D>
          <x>452.03</x>
          <y>297.08</y>
        </uav.map.converter.map.Point2D>
      </coordenates>
    </uav.map.converter.map.Poly2D>
    <uav.map.converter.map.Poly2D>
      <nameRegion>4</nameRegion>
      <typeRegion>NFZ_REGION</typeRegion>
      <coordenates>
        <uav.map.converter.map.Point2D>
          <x>243.56</x>
          <y>187.77</y>
        </uav.map.converter.map.Point2D>
        <uav.map.converter.map.Point2D>
          <x>157.19</x>
          <y>139.29</y>
        </uav.map.converter.map.Point2D>
        <uav.map.converter.map.Point2D>
          <x>108.72</x>
          <y>225.66</y>
        </uav.map.converter.map.Point2D>
        <uav.map.converter.map.Point2D>
          <x>195.08</x>
          <y>274.13</y>
        </uav.map.converter.map.Point2D>
      </coordenates>
    </uav.map.converter.map.Poly2D>
    <uav.map.converter.map.Poly2D>
      <nameRegion>0</nameRegion>
      <typeRegion>PENALTY_REGION</typeRegion>
      <coordenates>
        <uav.map.converter.map.Point2D>
          <x>274.01</x>
          <y>474.23</y>
        </uav.map.converter.map.Point2D>
        <uav.map.converter.map.Point2D>
          <x>262.64</x>
          <y>392.56</y>
        </uav.map.converter.map.Point2D>
        <uav.map.converter.map.Point2D>
          <x>180.97</x>
          <y>403.92</y>
        </uav.map.converter.map.Point2D>
        <uav.map.converter.map.Point2D>
          <x>192.33</x>
          <y>485.6</y>
        </uav.map.converter.map.Point2D>
      </coordenates>
    </uav.map.converter.map.Poly2D>
    <uav.map.converter.map.Poly2D>
      <nameRegion>1</nameRegion>
      <typeRegion>PENALTY_REGION</typeRegion>
      <coordenates>
        <uav.map.converter.map.Point2D>
          <x>414.15</x>
          <y>-296.83</y>
        </uav.map.converter.map.Point2D>
        <uav.map.converter.map.Point2D>
          <x>341.08</x>
          <y>-154.78</y>
        </uav.map.converter.map.Point2D>
        <uav.map.converter.map.Point2D>
          <x>483.12</x>
          <y>-81.7</y>
        </uav.map.converter.map.Point2D>
        <uav.map.converter.map.Point2D>
          <x>556.2</x>
          <y>-223.75</y>
        </uav.map.converter.map.Point2D>
      </coordenates>
    </uav.map.converter.map.Poly2D>
    <uav.map.converter.map.Poly2D>
      <nameRegion>2</nameRegion>
      <typeRegion>PENALTY_REGION</typeRegion>
      <coordenates>
        <uav.map.converter.map.Point2D>
          <x>423.8</x>
          <y>451.16</y>
        </uav.map.converter.map.Point2D>
        <uav.map.converter.map.Point2D>
          <x>368.02</x>
          <y>359.32</y>
        </uav.map.converter.map.Point2D>
        <uav.map.converter.map.Point2D>
          <x>276.18</x>
          <y>415.09</y>
        </uav.map.converter.map.Point2D>
        <uav.map.converter.map.Point2D>
          <x>331.96</x>
          <y>506.93</y>
        </uav.map.converter.map.Point2D>
      </coordenates>
    </uav.map.converter.map.Poly2D>
    <uav.map.converter.map.Poly2D>
      <nameRegion>3</nameRegion>
      <typeRegion>PENALTY_REGION</typeRegion>
      <coordenates>
        <uav.map.converter.map.Point2D>
          <x>-418.34</x>
          <y>-540.32</y>
        </uav.map.converter.map.Point2D>
        <uav.map.converter.map.Point2D>
          <x>-552.22</x>
          <y>-363.83</y>
        </uav.map.converter.map.Point2D>
        <uav.map.converter.map.Point2D>
          <x>-375.73</x>
          <y>-229.94</y>
        </uav.map.converter.map.Point2D>
        <uav.map.converter.map.Point2D>
          <x>-241.85</x>
          <y>-406.43</y>
        </uav.map.converter.map.Point2D>
      </coordenates>
    </uav.map.converter.map.Poly2D>
    <uav.map.converter.map.Poly2D>
      <nameRegion>0</nameRegion>
      <typeRegion>BONUS_REGION</typeRegion>
      <coordenates>
        <uav.map.converter.map.Point2D>
          <x>62.67</x>
          <y>320.56</y>
        </uav.map.converter.map.Point2D>
        <uav.map.converter.map.Point2D>
          <x>-74.15</x>
          <y>234.08</y>
        </uav.map.converter.map.Point2D>
        <uav.map.converter.map.Point2D>
          <x>-160.62</x>
          <y>370.91</y>
        </uav.map.converter.map.Point2D>
        <uav.map.converter.map.Point2D>
          <x>-23.8</x>
          <y>457.39</y>
        </uav.map.converter.map.Point2D>
      </coordenates>
    </uav.map.converter.map.Poly2D>
  </regions>
</uav.map.converter.map.Map>