{
  "regions": [
    {
      "nameRegion": "0",
      "typeRegion": "NFZ_REGION",
      "coordenates": [
        {
          "x": 533.12,
          "y": 174.13
        },
        {
          "x": 521.09,
          "y": 57.74
        },
        {
          "x": 404.7,
          "y": 69.78
        },
        {
          "x": 416.73,
          "y": 186.17
        }
      ]
    },
    {
      "nameRegion": "1",
      "typeRegion": "NFZ_REGION",
      "coordenates": [
        {
          "x": -318.65,
          "y": -442.32
        },
        {
          "x": -375.4,
          "y": -298.52
        },
        {
          "x": -231.6,
          "y": -241.76
        },
        {
          "x": -174.84,
          "y": -385.57
        }
      ]
    },
    {
      "nameRegion": "2",
      "typeRegion": "NFZ_REGION",
      "coordenates": [
        {
          "x": 78.0,
          "y": 141.25
        },
        {
          "x": -47.69,
          "y": 245.47
        },
        {
          "x": 56.51,
          "y": 371.17
        },
        {
          "x": 182.21,
          "y": 266.96
        }
      ]
    },
    {
      "nameRegion": "3",
      "typeRegion": "NFZ_REGION",
      "coordenates": [
        {
          "x": -112.86,
          "y": 488.51
        },
        {
          "x": -205.31,
          "y": 308.11
        },
        {
          "x": -385.71,
          "y": 400.56
        },
        {
          "x": -293.27,
          "y": 580.96
        }
      ]
    },
    {
      "nameRegion": "4",
      "typeRegion": "NFZ_REGION",
      "coordenates": [
        {
          "x": 271.84,
          "y": -494.49
        },
        {
          "x": 49.97,
          "y": -471.37
        },
        {
          "x": 73.09,
          "y": -249.51
        },
        {
          "x": 294.95,
          "y": -272.62
        }
      ]
    },
    {
      "nameRegion": "0",
      "typeRegion": "PENALTY_REGION",
      "coordenates": [
        {
          "x": 363.8,
          "y": 459.1
        },
        {
          "x": 363.78,
          "y": 496.61
        },
        {
          "x": 401.29,
          "y": 496.64
        },
        {
          "x": 401.32,
          "y": 459.12
        }
      ]
    },
    {
      "nameRegion": "1",
      "typeRegion": "PENALTY_REGION",
      "coordenates": [
        {
          "x": -217.46,
          "y": 111.26
        },
        {
          "x": -263.61,
          "y": -21.98
        },
        {
          "x": -396.86,
          "y": 24.16
        },
        {
          "x": -350.71,
          "y": 157.41
        }
      ]
    },
    {
      "nameRegion": "2",
      "typeRegion": "PENALTY_REGION",
      "coordenates": [
        {
          "x": 357.73,
          "y": 268.72
        },
        {
          "x": 310.78,
          "y": 179.81
        },
        {
          "x": 221.87,
          "y": 226.76
        },
        {
          "x": 268.82,
          "y": 315.67
        }
      ]
    },
    {
      "nameRegion": "3",
      "typeRegion": "PENALTY_REGION",
      "coordenates": [
        {
          "x": 57.32,
          "y": -340.0
        },
        {
          "x": -170.63,
          "y": -358.92
        },
        {
          "x": -189.55,
          "y": -130.96
        },
        {
          "x": 38.4,
          "y": -112.04
        }
      ]
    },
    {
      "nameRegion": "4",
      "typeRegion": "PENALTY_REGION",
      "coordenates": [
        {
          "x": 385.04,
          "y": -365.18
        },
        {
          "x": 324.09,
          "y": -317.78
        },
        {
          "x": 371.49,
          "y": -256.83
        },
        {
          "x": 432.44,
          "y": -304.24
        }
      ]
    },
    {
      "nameRegion": "5",
      "typeRegion": "PENALTY_REGION",
      "coordenates": [
        {
          "x": 219.99,
          "y": -74.75
        },
        {
          "x": 189.87,
          "y": -162.75
        },
        {
          "x": 101.87,
          "y": -132.63
        },
        {
          "x": 131.99,
          "y": -44.63
        }
      ]
    },
    {
      "nameRegion": "6",
      "typeRegion": "PENALTY_REGION",
      "coordenates": [
        {
          "x": -447.83,
          "y": 447.77
        },
        {
          "x": -501.47,
          "y": 415.41
        },
        {
          "x": -533.84,
          "y": 469.04
        },
        {
          "x": -480.2,
          "y": 501.41
        }
      ]
    },
    {
      "nameRegion": "7",
      "typeRegion": "PENALTY_REGION",
      "coordenates": [
        {
          "x": 291.76,
          "y": 11.79
        },
        {
          "x": 211.7,
          "y": 2.3
        },
        {
          "x": 202.21,
          "y": 82.36
        },
        {
          "x": 282.27,
          "y": 91.85
        }
      ]
    },
    {
      "nameRegion": "8",
      "typeRegion": "PENALTY_REGION",
      "coordenates": [
        {
          "x": 384.84,
          "y": -167.97
        },
        {
          "x": 333.76,
          "y": -61.9
        },
        {
          "x": 439.83,
          "y": -10.82
        },
        {
          "x": 490.91,
          "y": -116.89
        }
      ]
    },
    {
      "nameRegion": "9",
      "typeRegion": "PENALTY_REGION",
      "coordenates": [
        {
          "x": 381.75,
          "y": 331.74
        },
        {
          "x": 345.9,
          "y": 357.26
        },
        {
          "x": 371.42,
          "y": 393.11
        },
        {
          "x": 407.27,
          "y": 367.59
        }
      ]
    },
    {
      "nameRegion": "10",
      "typeRegion": "PENALTY_REGION",
      "coordenates": [
        {
          "x": -46.86,
          "y": 382.52
        },
        {
          "x": -100.56,
          "y": 474.29
        },
        {
          "x": -8.79,
          "y": 528.0
        },
        {
          "x": 44.9,
          "y": 436.23
        }
      ]
    },
    {
      "nameRegion": "11",
      "typeRegion": "PENALTY_REGION",
      "coordenates": [
        {
          "x": -304.39,
          "y": -167.0
        },
        {
          "x": -472.44,
          "y": -239.1
        },
        {
          "x": -544.54,
          "y": -71.05
        },
        {
          "x": -376.49,
          "y": 1.04
        }
      ]
    },
    {
      "nameRegion": "0",
      "typeRegion": "BONUS_REGION",
      "coordenates": [
        {
          "x": -382.93,
          "y": 246.05
        },
        {
          "x": -429.44,
          "y": 318.51
        },
        {
          "x": -356.99,
          "y": 365.02
        },
        {
          "x": -310.48,
          "y": 292.56
        }
      ]
    },
    {
      "nameRegion": "1",
      "typeRegion": "BONUS_REGION",
      "coordenates": [
        {
          "x": 41.82,
          "y": -60.15
        },
        {
          "x": -41.89,
          "y": -42.94
        },
        {
          "x": -24.68,
          "y": 40.77
        },
        {
          "x": 59.03,
          "y": 23.56
        }
      ]
    },
    {
      "nameRegion": "2",
      "typeRegion": "BONUS_REGION",
      "coordenates": [
        {
          "x": -187.41,
          "y": -123.62
        },
        {
          "x": -211.49,
          "y": -131.1
        },
        {
          "x": -218.97,
          "y": -107.02
        },
        {
          "x": -194.89,
          "y": -99.54
        }
      ]
    },
    {
      "nameRegion": "3",
      "typeRegion": "BONUS_REGION",
      "coordenates": [
        {
          "x": 510.78,
          "y": 342.12
        },
        {
          "x": 455.37,
          "y": 375.95
        },
        {
          "x": 489.2,
          "y": 431.36
        },
        {
          "x": 544.61,
          "y": 397.53
        }
      ]
    },
    {
      "nameRegion": "4",
      "typeRegion": "BONUS_REGION",
      "coordenates": [
        {
          "x": -38.55,
          "y": 94.43
        },
        {
          "x": -49.87,
          "y": 164.67
        },
        {
          "x": 20.36,
          "y": 175.98
        },
        {
          "x": 31.68,
          "y": 105.74
        }
      ]
    },
    {
      "nameRegion": "5",
      "typeRegion": "BONUS_REGION",
      "coordenates": [
        {
          "x": -81.13,
          "y": 203.99
        },
        {
          "x": -88.37,
          "y": 76.27
        },
        {
          "x": -216.09,
          "y": 83.5
        },
        {
          "x": -208.85,
          "y": 211.22
        }
      ]
    },
    {
      "nameRegion": "6",
      "typeRegion": "BONUS_REGION",
      "coordenates": [
        {
          "x": -127.25,
          "y": 271.15
        },
        {
          "x": -136.07,
          "y": 349.74
        },
        {
          "x": -57.48,
          "y": 358.56
        },
        {
          "x": -48.66,
          "y": 279.96
        }
      ]
    },
    {
      "nameRegion": "7",
      "typeRegion": "BONUS_REGION",
      "coordenates": [
        {
          "x": -408.54,
          "y": 69.67
        },
        {
          "x": -494.08,
          "y": 72.42
        },
        {
          "x": -491.33,
          "y": 157.97
        },
        {
          "x": -405.78,
          "y": 155.22
        }
      ]
    },
    {
      "nameRegion": "8",
      "typeRegion": "BONUS_REGION",
      "coordenates": [
        {
          "x": -358.2,
          "y": -391.32
        },
        {
          "x": -411.37,
          "y": -508.91
        },
        {
          "x": -528.96,
          "y": -455.74
        },
        {
          "x": -475.79,
          "y": -338.15
        }
      ]
    },
    {
      "nameRegion": "9",
      "typeRegion": "BONUS_REGION",
      "coordenates": [
        {
          "x": -201.73,
          "y": -58.98
        },
        {
          "x": -210.34,
          "y": 12.75
        },
        {
          "x": -138.6,
          "y": 21.36
        },
        {
          "x": -129.99,
          "y": -50.37
        }
      ]
    },
    {
      "nameRegion": "10",
      "typeRegion": "BONUS_REGION",
      "coordenates": [
        {
          "x": -420.35,
          "y": 297.53
        },
        {
          "x": -487.57,
          "y": 212.37
        },
        {
          "x": -572.74,
          "y": 279.59
        },
        {
          "x": -505.52,
          "y": 364.75
        }
      ]
    },
    {
      "nameRegion": "11",
      "typeRegion": "BONUS_REGION",
      "coordenates": [
        {
          "x": 467.62,
          "y": -411.74
        },
        {
          "x": 452.76,
          "y": -523.99
        },
        {
          "x": 340.51,
          "y": -509.12
        },
        {
          "x": 355.38,
          "y": -396.87
        }
      ]
    },
    {
      "nameRegion": "12",
      "typeRegion": "BONUS_REGION",
      "coordenates": [
        {
          "x": -292.7,
          "y": -458.45
        },
        {
          "x": -317.95,
          "y": -511.68
        },
        {
          "x": -371.19,
          "y": -486.43
        },
        {
          "x": -345.94,
          "y": -433.2
        }
      ]
    },
    {
      "nameRegion": "13",
      "typeRegion": "BONUS_REGION",
      "coordenates": [
        {
          "x": -40.74,
          "y": -503.49
        },
        {
          "x": -106.68,
          "y": -438.05
        },
        {
          "x": -41.24,
          "y": -372.11
        },
        {
          "x": 24.7,
          "y": -437.55
        }
      ]
    },
    {
      "nameRegion": "14",
      "typeRegion": "BONUS_REGION",
      "coordenates": [
        {
          "x": 167.95,
          "y": 414.75
        },
        {
          "x": 161.27,
          "y": 384.17
        },
        {
          "x": 130.68,
          "y": 390.86
        },
        {
          "x": 137.37,
          "y": 421.44
        }
      ]
    },
    {
      "nameRegion": "15",
      "typeRegion": "BONUS_REGION",
      "coordenates": [
        {
          "x": -250.92,
          "y": -227.57
        },
        {
          "x": -281.53,
          "y": -234.1
        },
        {
          "x": -288.06,
          "y": -203.5
        },
        {
          "x": -257.45,
          "y": -196.97
        }
      ]
    },
    {
      "nameRegion": "16",
      "typeRegion": "BONUS_REGION",
      "coordenates": [
        {
          "x": -243.29,
          "y": -119.36
        },
        {
          "x": -307.32,
          "y": -118.64
        },
        {
          "x": -306.6,
          "y": -54.61
        },
        {
          "x": -242.57,
          "y": -55.33
        }
      ]
    },
    {
      "nameRegion": "17",
      "typeRegion": "BONUS_REGION",
      "coordenates": [
        {
          "x": -249.79,
          "y": 189.93
        },
        {
          "x": -324.36,
          "y": 245.74
        },
        {
          "x": -268.55,
          "y": 320.31
        },
        {
          "x": -193.98,
          "y": 264.5
        }
      ]
    },
    {
      "nameRegion": "18",
      "typeRegion": "BONUS_REGION",
      "coordenates": [
        {
          "x": 244.26,
          "y": 318.68
        },
        {
          "x": 232.04,
          "y": 269.35
        },
        {
          "x": 182.71,
          "y": 281.56
        },
        {
          "x": 194.93,
          "y": 330.9
        }
      ]
    },
    {
      "nameRegion": "19",
      "typeRegion": "BONUS_REGION",
      "coordenates": [
        {
          "x": 153.53,
          "y": 516.49
        },
        {
          "x": 116.94,
          "y": 432.04
        },
        {
          "x": 32.48,
          "y": 468.63
        },
        {
          "x": 69.07,
          "y": 553.08
        }
      ]
    },
    {
      "nameRegion": "20",
      "typeRegion": "BONUS_REGION",
      "coordenates": [
        {
          "x": -434.73,
          "y": -271.46
        },
        {
          "x": -452.94,
          "y": -249.95
        },
        {
          "x": -431.43,
          "y": -231.75
        },
        {
          "x": -413.22,
          "y": -253.26
        }
      ]
    },
    {
      "nameRegion": "21",
      "typeRegion": "BONUS_REGION",
      "coordenates": [
        {
          "x": 428.08,
          "y": -254.91
        },
        {
          "x": 416.38,
          "y": -175.24
        },
        {
          "x": 496.05,
          "y": -163.54
        },
        {
          "x": 507.75,
          "y": -243.21
        }
      ]
    },
    {
      "nameRegion": "22",
      "typeRegion": "BONUS_REGION",
      "coordenates": [
        {
          "x": 160.09,
          "y": 59.39
        },
        {
          "x": 111.25,
          "y": 47.92
        },
        {
          "x": 99.79,
          "y": 96.76
        },
        {
          "x": 148.63,
          "y": 108.22
        }
      ]
    },
    {
      "nameRegion": "23",
      "typeRegion": "BONUS_REGION",
      "coordenates": [
        {
          "x": 306.37,
          "y": 322.73
        },
        {
          "x": 182.87,
          "y": 398.98
        },
        {
          "x": 259.11,
          "y": 522.48
        },
        {
          "x": 382.62,
          "y": 446.24
        }
      ]
    },
    {
      "nameRegion": "24",
      "typeRegion": "BONUS_REGION",
      "coordenates": [
        {
          "x": -78.99,
          "y": -107.1
        },
        {
          "x": -100.22,
          "y": -90.37
        },
        {
          "x": -83.5,
          "y": -69.14
        },
        {
          "x": -62.26,
          "y": -85.87
        }
      ]
    },
    {
      "nameRegion": "25",
      "typeRegion": "BONUS_REGION",
      "coordenates": [
        {
          "x": 330.17,
          "y": 61.68
        },
        {
          "x": 300.82,
          "y": 72.84
        },
        {
          "x": 311.98,
          "y": 102.19
        },
        {
          "x": 341.33,
          "y": 91.03
        }
      ]
    },
    {
      "nameRegion": "26",
      "typeRegion": "BONUS_REGION",
      "coordenates": [
        {
          "x": 247.98,
          "y": -236.97
        },
        {
          "x": 186.56,
          "y": -173.25
        },
        {
          "x": 250.28,
          "y": -111.83
        },
        {
          "x": 311.7,
          "y": -175.55
        }
      ]
    }
  ]
}
