<uav.map.converter.map.Map>
  <regions>
    <uav.map.converter.map.Poly2D>
      <nameRegion>0</nameRegion>
      <typeRegion>NFZ_REGION</typeRegion>
      <coordenates>
        <uav.map.converter.map.Point2D>
          <x>334.82</x>
          <y>-1.41</y>
        </uav.map.converter.map.Point2D>
        <uav.map.converter.map.Point2D>
          <x>140.4</x>
          <y>-59.06</y>
        </uav.map.converter.map.Point2D>
        <uav.map.converter.map.Point2D>
          <x>82.75</x>
          <y>135.35</y>
        </uav.map.converter.map.Point2D>
        <uav.map.converter.map.Point2D>
          <x>277.17</x>
          <y>193.0</y>
        </uav.map.converter.map.Point2D>
      </coordenates>
    </uav.map.converter.map.Poly2D>
    <uav.map.converter.map.Poly2D>
      <nameRegion>1</nameRegion>
      <typeRegion>NFZ_REGION</typeRegion>
      <coordenates>
        <uav.map.converter.map.Point2D>
          <x>140.49</x>
          <y>527.02</y>
        </uav.map.converter.map.Point2D>
        <uav.map.converter.map.Point2D>
          <x>35.52</x>
          <y>310.0</y>
        </uav.map.converter.map.Point2D>
        <uav.map.converter.map.Point2D>
          <x>-181.48</x>
          <y>414.96</y>
        </uav.map.converter.map.Point2D>
        <uav.map.converter.map.Point2D>
          <x>-76.52</x>
          <y>631.98</y>
        </uav.map.converter.map.Point2D>
      </coordenates>
    </uav.map.converter.map.Poly2D>
    <uav.map.converter.map.Poly2D>
      <nameRegion>2</nameRegion>
      <typeRegion>NFZ_REGION</typeRegion>
      <coordenates>
        <uav.map.converter.map.Point2D>
          <x>-389.11</x>
          <y>-381.19</y>
        </uav.map.converter.map.Point2D>
        <uav.map.converter.map.Point2D>
          <x>-490.92</x>
          <y>-320.29</y>
        </uav.map.converter.map.Point2D>
        <uav.map.converter.map.Point2D>
          <x>-430.01</x>
          <y>-218.48</y>
        </uav.map.converter.map.Point2D>
        <uav.map.converter.map.Point2D>
          <x>-328.21</x>
          <y>-279.39</y>
        </uav.map.converter.map.Point2D>
      </coordenates>
    </uav.map.converter.map.Poly2D>
    <uav.map.converter.map.Poly2D>
      <nameRegion>3</nameRegion>
      <typeRegion>NFZ_REGION</typeRegion>
      <coordenates>
        <uav.map.converter.map.Point2D>
          <x>230.16</x>
          <y>-418.79</y>
        </uav.map.converter.map.Point2D>
        <uav.map.converter.map.Point2D>
          <x>154.03</x>
          <y>-413.47</y>
        </uav.map.converter.map.Point2D>
        <uav.map.converter.map.Point2D>
          <x>159.36</x>
          <y>-337.34</y>
        </uav.map.converter.map.Point2D>
        <uav.map.converter.map.Point2D>
          <x>235.48</x>
          <y>-342.67</y>
        </uav.map.converter.map.Point2D>
      </coordenates>
    </uav.map.converter.map.Poly2D>
    <uav.map.converter.map.Poly2D>
      <nameRegion>4</nameRegion>
      <typeRegion>NFZ_REGION</typeRegion>
      <coordenates>
        <uav.map.converter.map.Point2D>
          <x>425.55</x>
          <y>361.39</y>
        </uav.map.converter.map.Point2D>
        <uav.map.converter.map.Point2D>
          <x>417.61</x>
          <y>458.69</y>
        </uav.map.converter.map.Point2D>
        <uav.map.converter.map.Point2D>
          <x>514.91</x>
          <y>466.64</y>
        </uav.map.converter.map.Point2D>
        <uav.map.converter.map.Point2D>
          <x>522.85</x>
          <y>369.33</y>
        </uav.map.converter.map.Point2D>
      </coordenates>
    </uav.map.converter.map.Poly2D>
    <uav.map.converter.map.Poly2D>
      <nameRegion>5</nameRegion>
      <typeRegion>NFZ_REGION</typeRegion>
      <coordenates>
        <uav.map.converter.map.Point2D>
          <x>51.87</x>
          <y>-330.71</y>
        </uav.map.converter.map.Point2D>
        <uav.map.converter.map.Point2D>
          <x>-32.99</x>
          <y>-198.72</y>
        </uav.map.converter.map.Point2D>
        <uav.map.converter.map.Point2D>
          <x>98.99</x>
          <y>-113.84</y>
        </uav.map.converter.map.Point2D>
        <uav.map.converter.map.Point2D>
          <x>183.86</x>
          <y>-245.83</y>
        </uav.map.converter.map.Point2D>
      </coordenates>
    </uav.map.converter.map.Poly2D>
    <uav.map.converter.map.Poly2D>
      <nameRegion>0</nameRegion>
      <typeRegion>PENALTY_REGION</typeRegion>
      <coordenates>
        <uav.map.converter.map.Point2D>
          <x>561.54</x>
          <y>-270.63</y>
        </uav.map.converter.map.Point2D>
        <uav.map.converter.map.Point2D>
          <x>467.85</x>
          <y>-428.91</y>
        </uav.map.converter.map.Point2D>
        <uav.map.converter.map.Point2D>
          <x>309.57</x>
          <y>-335.22</y>
        </uav.map.converter.map.Point2D>
        <uav.map.converter.map.Point2D>
          <x>403.26</x>
          <y>-176.94</y>
        </uav.map.converter.map.Point2D>
      </coordenates>
    </uav.map.converter.map.Poly2D>
    <uav.map.converter.map.Poly2D>
      <nameRegion>1</nameRegion>
      <typeRegion>PENALTY_REGION</typeRegion>
      <coordenates>
        <uav.map.converter.map.Point2D>
          <x>-141.79</x>
          <y>-399.73</y>
        </uav.map.converter.map.Point2D>
        <uav.map.converter.map.Point2D>
          <x>-261.54</x>
          <y>-320.8</y>
        </uav.map.converter.map.Point2D>
        <uav.map.converter.map.Point2D>
          <x>-182.62</x>
          <y>-201.05</y>
        </uav.map.converter.map.Point2D>
        <uav.map.converter.map.Point2D>
          <x>-62.86</x>
          <y>-279.97</y>
        </uav.map.converter.map.Point2D>
      </coordenates>
    </uav.map.converter.map.Poly2D>
    <uav.map.converter.map.Poly2D>
      <nameRegion>2</nameRegion>
      <typeRegion>PENALTY_REGION</typeRegion>
      <coordenates>
        <uav.map.converter.map.Point2D>
          <x>564.43</x>
          <y>-149.84</y>
        </uav.map.converter.map.Point2D>
        <uav.map.converter.map.Point2D>
          <x>378.75</x>
          <y>-167.67</y>
        </uav.map.converter.map.Point2D>
        <uav.map.converter.map.Point2D>
          <x>360.92</x>
          <y>18.0</y>
        </uav.map.converter.map.Point2D>
        <uav.map.converter.map.Point2D>
          <x>546.6</x>
          <y>35.84</y>
        </uav.map.converter.map.Point2D>
      </coordenates>
    </uav.map.converter.map.Poly2D>
    <uav.map.converter.map.Poly2D>
      <nameRegion>3</nameRegion>
      <typeRegion>PENALTY_REGION</typeRegion>
      <coordenates>
        <uav.map.converter.map.Point2D>
          <x>-233.71</x>
          <y>410.08</y>
        </uav.map.converter.map.Point2D>
        <uav.map.converter.map.Point2D>
          <x>-243.2</x>
          <y>455.53</y>
        </uav.map.converter.map.Point2D>
        <uav.map.converter.map.Point2D>
          <x>-197.76</x>
          <y>465.02</y>
        </uav.map.converter.map.Point2D>
        <uav.map.converter.map.Point2D>
          <x>-188.26</x>
          <y>419.57</y>
        </uav.map.converter.map.Point2D>
      </coordenates>
    </uav.map.converter.map.Poly2D>
    <uav.map.converter.map.Poly2D>
      <nameRegion>4</nameRegion>
      <typeRegion>PENALTY_REGION</typeRegion>
      <coordenates>
        <uav.map.converter.map.Point2D>
          <x>-168.87</x>
          <y>143.71</y>
        </uav.map.converter.map.Point2D>
        <uav.map.converter.map.Point2D>
          <x>-232.36</x>
          <y>42.66</y>
        </uav.map.converter.map.Point2D>
        <uav.map.converter.map.Point2D>
          <x>-333.41</x>
          <y>106.16</y>
        </uav.map.converter.map.Point2D>
        <uav.map.converter.map.Point2D>
          <x>-269.91</x>
          <y>207.21</y>
        </uav.map.converter.map.Point2D>
      </coordenates>
    </uav.map.converter.map.Poly2D>
    <uav.map.converter.map.Poly2D>
      <nameRegion>5</nameRegion>
      <typeRegion>PENALTY_REGION</typeRegion>
      <coordenates>
        <uav.map.converter.map.Point2D>
          <x>370.63</x>
          <y>292.04</y>
        </uav.map.converter.map.Point2D>
        <uav.map.converter.map.Point2D>
          <x>217.55</x>
          <y>336.81</y>
        </uav.map.converter.map.Point2D>
        <uav.map.converter.map.Point2D>
          <x>262.32</x>
          <y>489.89</y>
        </uav.map.converter.map.Point2D>
        <uav.map.converter.map.Point2D>
          <x>415.39</x>
          <y>445.12</y>
        </uav.map.converter.map.Point2D>
      </coordenates>
    </uav.map.converter.map.Poly2D>
    <uav.map.converter.map.Poly2D>
      <nameRegion>6</nameRegion>
      <typeRegion>PENALTY_REGION</typeRegion>
      <coordenates>
        <uav.map.converter.map.Point2D>
          <x>537.12</x>
          <y>242.86</y>
        </uav.map.converter.map.Point2D>
        <uav.map.converter.map.Point2D>
          <x>514.17</x>
          <y>148.99</y>
        </uav.map.converter.map.Point2D>
        <uav.map.converter.map.Point2D>
          <x>420.29</x>
          <y>171.95</y>
        </uav.map.converter.map.Point2D>
        <uav.map.converter.map.Point2D>
          <x>443.25</x>
          <y>265.82</y>
        </uav.map.converter.map.Point2D>
      </coordenates>
    </uav.map.converter.map.Poly2D>
    <uav.map.converter.map.Poly2D>
      <nameRegion>7</nameRegion>
      <typeRegion>PENALTY_REGION</typeRegion>
      <coordenates>
        <uav.map.converter.map.Point2D>
          <x>-125.74</x>
          <y>-79.55</y>
        </uav.map.converter.map.Point2D>
        <uav.map.converter.map.Point2D>
          <x>-256.21</x>
          <y>-152.95</y>
        </uav.map.converter.map.Point2D>
        <uav.map.converter.map.Point2D>
          <x>-329.6</x>
          <y>-22.48</y>
        </uav.map.converter.map.Point2D>
        <uav.map.converter.map.Point2D>
          <x>-199.14</x>
          <y>50.9</y>
        </uav.map.converter.map.Point2D>
      </coordenates>
    </uav.map.converter.map.Poly2D>
    <uav.map.converter.map.Poly2D>
      <nameRegion>0</nameRegion>
      <typeRegion>BONUS_REGION</typeRegion>
      <coordenates>
        <uav.map.converter.map.Point2D>
          <x>61.39</x>
          <y>61.64</y>
        </uav.map.converter.map.Point2D>
        <uav.map.converter.map.Point2D>
          <x>-58.7</x>
          <y>-13.99</y>
        </uav.map.converter.map.Point2D>
        <uav.map.converter.map.Point2D>
          <x>-134.33</x>
          <y>106.11</y>
        </uav.map.converter.map.Point2D>
        <uav.map.converter.map.Point2D>
          <x>-14.23</x>
          <y>181.74</y>
        </uav.map.converter.map.Point2D>
      </coordenates>
    </uav.map.converter.map.Poly2D>
    <uav.map.converter.map.Poly2D>
      <nameRegion>1</nameRegion>
      <typeRegion>BONUS_REGION</typeRegion>
      <coordenates>
        <uav.map.converter.map.Point2D>
          <x>-289.93</x>
          <y>440.5</y>
        </uav.map.converter.map.Point2D>
        <uav.map.converter.map.Point2D>
          <x>-310.56</x>
          <y>323.5</y>
        </uav.map.converter.map.Point2D>
        <uav.map.converter.map.Point2D>
          <x>-427.56</x>
          <y>344.12</y>
        </uav.map.converter.map.Point2D>
        <uav.map.converter.map.Point2D>
          <x>-406.93</x>
          <y>461.12</y>
        </uav.map.converter.map.Point2D>
      </coordenates>
    </uav.map.converter.map.Poly2D>
    <uav.map.converter.map.Poly2D>
      <nameRegion>2</nameRegion>
      <typeRegion>BONUS_REGION</typeRegion>
      <coordenates>
        <uav.map.converter.map.Point2D>
          <x>-302.09</x>
          <y>1.04</y>
        </uav.map.converter.map.Point2D>
        <uav.map.converter.map.Point2D>
          <x>-458.23</x>
          <y>-69.45</y>
        </uav.map.converter.map.Point2D>
        <uav.map.converter.map.Point2D>
          <x>-528.73</x>
          <y>86.69</y>
        </uav.map.converter.map.Point2D>
        <uav.map.converter.map.Point2D>
          <x>-372.59</x>
          <y>157.19</y>
        </uav.map.converter.map.Point2D>
      </coordenates>
    </uav.map.converter.map.Poly2D>
    <uav.map.converter.map.Poly2D>
      <nameRegion>3</nameRegion>
      <typeRegion>BONUS_REGION</typeRegion>
      <coordenates>
        <uav.map.converter.map.Point2D>
          <x>-224.14</x>
          <y>-420.23</y>
        </uav.map.converter.map.Point2D>
        <uav.map.converter.map.Point2D>
          <x>-231.14</x>
          <y>-466.49</y>
        </uav.map.converter.map.Point2D>
        <uav.map.converter.map.Point2D>
          <x>-277.41</x>
          <y>-459.49</y>
        </uav.map.converter.map.Point2D>
        <uav.map.converter.map.Point2D>
          <x>-270.4</x>
          <y>-413.22</y>
        </uav.map.converter.map.Point2D>
      </coordenates>
    </uav.map.converter.map.Poly2D>
    <uav.map.converter.map.Poly2D>
      <nameRegion>4</nameRegion>
      <typeRegion>BONUS_REGION</typeRegion>
      <coordenates>
        <uav.map.converter.map.Point2D>
          <x>12.72</x>
          <y>197.93</y>
        </uav.map.converter.map.Point2D>
        <uav.map.converter.map.Point2D>
          <x>-64.18</x>
          <y>182.38</y>
        </uav.map.converter.map.Point2D>
        <uav.map.converter.map.Point2D>
          <x>-79.73</x>
          <y>259.29</y>
        </uav.map.converter.map.Point2D>
        <uav.map.converter.map.Point2D>
          <x>-2.82</x>
          <y>274.84</y>
        </uav.map.converter.map.Point2D>
      </coordenates>
    </uav.map.converter.map.Poly2D>
    <uav.map.converter.map.Poly2D>
      <nameRegion>5</nameRegion>
      <typeRegion>BONUS_REGION</typeRegion>
      <coordenates>
        <uav.map.converter.map.Point2D>
          <x>341.32</x>
          <y>-155.19</y>
        </uav.map.converter.map.Point2D>
        <uav.map.converter.map.Point2D>
          <x>225.41</x>
          <y>-186.98</y>
        </uav.map.converter.map.Point2D>
        <uav.map.converter.map.Point2D>
          <x>193.62</x>
          <y>-71.07</y>
        </uav.map.converter.map.Point2D>
        <uav.map.converter.map.Point2D>
          <x>309.53</x>
          <y>-39.27</y>
        </uav.map.converter.map.Point2D>
      </coordenates>
    </uav.map.converter.map.Poly2D>
    <uav.map.converter.map.Poly2D>
      <nameRegion>6</nameRegion>
      <typeRegion>BONUS_REGION</typeRegion>
      <coordenates>
        <uav.map.converter.map.Point2D>
          <x>-454.15</x>
          <y>140.88</y>
        </uav.map.converter.map.Point2D>
        <uav.map.converter.map.Point2D>
          <x>-569.19</x>
          <y>236.98</y>
        </uav.map.converter.map.Point2D>
        <uav.map.converter.map.Point2D>
          <x>-473.09</x>
          <y>352.02</y>
        </uav.map.converter.map.Point2D>
        <uav.map.converter.map.Point2D>
          <x>-358.05</x>
          <y>255.91</y>
        </uav.map.converter.map.Point2D>
      </coordenates>
    </uav.map.converter.map.Poly2D>
    <uav.map.converter.map.Poly2D>
      <nameRegion>7</nameRegion>
      <typeRegion>BONUS_REGION</typeRegion>
      <coordenates>
        <uav.map.converter.map.Point2D>
          <x>325.25</x>
          <y>141.02</y>
        </uav.map.converter.map.Point2D>
        <uav.map.converter.map.Point2D>
          <x>262.51</x>
          <y>217.87</y>
        </uav.map.converter.map.Point2D>
        <uav.map.converter.map.Point2D>
          <x>339.36</x>
          <y>280.62</y>
        </uav.map.converter.map.Point2D>
        <uav.map.converter.map.Point2D>
          <x>402.1</x>
          <y>203.77</y>
        </uav.map.converter.map.Point2D>
      </coordenates>
    </uav.map.converter.map.Poly2D>
    <uav.map.converter.map.Poly2D>
      <nameRegion>8</nameRegion>
      <typeRegion>BONUS_REGION</typeRegion>
      <coordenates>
        <uav.map.converter.map.Point2D>
          <x>-140.53</x>
          <y>240.11</y>
        </uav.map.converter.map.Point2D>
        <uav.map.converter.map.Point2D>
          <x>-155.13</x>
          <y>185.7</y>
        </uav.map.converter.map.Point2D>
        <uav.map.converter.map.Point2D>
          <x>-209.53</x>
          <y>200.3</y>
        </uav.map.converter.map.Point2D>
        <uav.map.converter.map.Point2D>
          <x>-194.94</x>
          <y>254.71</y>
        </uav.map.converter.map.Point2D>
      </coordenates>
    </uav.map.converter.map.Poly2D>
    <uav.map.converter.map.Poly2D>
      <nameRegion>9</nameRegion>
      <typeRegion>BONUS_REGION</typeRegion>
      <coordenates>
        <uav.map.converter.map.Point2D>
          <x>-121.03</x>
          <y>257.91</y>
        </uav.map.converter.map.Point2D>
        <uav.map.converter.map.Point2D>
          <x>-229.26</x>
          <y>278.37</y>
        </uav.map.converter.map.Point2D>
        <uav.map.converter.map.Point2D>
          <x>-208.79</x>
          <y>386.6</y>
        </uav.map.converter.map.Point2D>
        <uav.map.converter.map.Point2D>
          <x>-100.56</x>
          <y>366.14</y>
        </uav.map.converter.map.Point2D>
      </coordenates>
    </uav.map.converter.map.Poly2D>
    <uav.map.converter.map.Poly2D>
      <nameRegion>10</nameRegion>
      <typeRegion>BONUS_REGION</typeRegion>
      <coordenates>
        <uav.map.converter.map.Point2D>
          <x>8.37</x>
          <y>-562.41</y>
        </uav.map.converter.map.Point2D>
        <uav.map.converter.map.Point2D>
          <x>-132.8</x>
          <y>-466.04</y>
        </uav.map.converter.map.Point2D>
        <uav.map.converter.map.Point2D>
          <x>-36.44</x>
          <y>-324.86</y>
        </uav.map.converter.map.Point2D>
        <uav.map.converter.map.Point2D>
          <x>104.73</x>
          <y>-421.23</y>
        </uav.map.converter.map.Point2D>
      </coordenates>
    </uav.map.converter.map.Poly2D>
    <uav.map.converter.map.Poly2D>
      <nameRegion>11</nameRegion>
      <typeRegion>BONUS_REGION</typeRegion>
      <coordenates>
        <uav.map.converter.map.Point2D>
          <x>-276.76</x>
          <y>-404.72</y>
        </uav.map.converter.map.Point2D>
        <uav.map.converter.map.Point2D>
          <x>-322.66</x>
          <y>-392.19</y>
        </uav.map.converter.map.Point2D>
        <uav.map.converter.map.Point2D>
          <x>-310.12</x>
          <y>-346.29</y>
        </uav.map.converter.map.Point2D>
        <uav.map.converter.map.Point2D>
          <x>-264.23</x>
          <y>-358.83</y>
        </uav.map.converter.map.Point2D>
      </coordenates>
    </uav.map.converter.map.Poly2D>
    <uav.map.converter.map.Poly2D>
      <nameRegion>12</nameRegion>
      <typeRegion>BONUS_REGION</typeRegion>
      <coordenates>
        <uav.map.converter.map.Point2D>
          <x>196.73</x>
          <y>461.76</y>
        </uav.map.converter.map.Point2D>
        <uav.map.converter.map.Point2D>
          <x>158.29</x>
          <y>499.68</y>
        </uav.map.converter.map.Point2D>
        <uav.map.converter.map.Point2D>
          <x>196.21</x>
          <y>538.12</y>
        </uav.map.converter.map.Point2D>
        <uav.map.converter.map.Point2D>
          <x>234.65</x>
          <y>500.19</y>
        </uav.map.converter.map.Point2D>
      </coordenates>
    </uav.map.converter.map.Poly2D>
    <uav.map.converter.map.Poly2D>
      <nameRegion>13</nameRegion>
      <typeRegion>BONUS_REGION</typeRegion>
      <coordenates>
        <uav.map.converter.map.Point2D>
          <x>320.49</x>
          <y>-491.7</y>
        </uav.map.converter.map.Point2D>
        <uav.map.converter.map.Point2D>
          <x>296.85</x>
          <y>-414.05</y>
        </uav.map.converter.map.Point2D>
        <uav.map.converter.map.Point2D>
          <x>374.5</x>
          <y>-390.42</y>
        </uav.map.converter.map.Point2D>
        <uav.map.converter.map.Point2D>
          <x>398.13</x>
          <y>-468.06</y>
        </uav.map.converter.map.Point2D>
      </coordenates>
    </uav.map.converter.map.Poly2D>
    <uav.map.converter.map.Poly2D>
      <nameRegion>14</nameRegion>
      <typeRegion>BONUS_REGION</typeRegion>
      <coordenates>
        <uav.map.converter.map.Point2D>
          <x>-483.1</x>
          <y>348.78</y>
        </uav.map.converter.map.Point2D>
        <uav.map.converter.map.Point2D>
          <x>-569.81</x>
          <y>402.1</y>
        </uav.map.converter.map.Point2D>
        <uav.map.converter.map.Point2D>
          <x>-516.49</x>
          <y>488.8</y>
        </uav.map.converter.map.Point2D>
        <uav.map.converter.map.Point2D>
          <x>-429.78</x>
          <y>435.48</y>
        </uav.map.converter.map.Point2D>
      </coordenates>
    </uav.map.converter.map.Poly2D>
  </regions>
</uav.map.converter.map.Map>