{
  "regions": [
    {
      "nameRegion": "0",
      "typeRegion": "NFZ_REGION",
      "coordenates": [
        {
          "x": -429.51,
          "y": 367.53
        },
        {
          "x": -444.54,
          "y": 502.18
        },
        {
          "x": -309.89,
          "y": 517.22
        },
        {
          "x": -294.85,
          "y": 382.56
        }
      ]
    },
    {
      "nameRegion": "1",
      "typeRegion": "NFZ_REGION",
      "coordenates": [
        {
          "x": -426.0,
          "y": -113.98
        },
        {
          "x": -467.36,
          "y": -65.42
        },
        {
          "x": -418.8,
          "y": -24.06
        },
        {
          "x": -377.44,
          "y": -72.61
        }
      ]
    },
    {
      "nameRegion": "2",
      "typeRegion": "NFZ_REGION",
      "coordenates": [
        {
          "x": 164.38,
          "y": -329.34
        },
        {
          "x": 59.04,
          "y": -274.82
        },
        {
          "x": 113.55,
          "y": -169.48
        },
        {
          "x": 218.9,
          "y": -223.99
        }
      ]
    },
    {
      "nameRegion": "3",
      "typeRegion": "NFZ_REGION",
      "coordenates": [
        {
          "x": 547.38,
          "y": 199.97
        },
        {
          "x": 354.34,
          "y": 218.61
        },
        {
          "x": 372.98,
          "y": 411.64
        },
        {
          "x": 566.01,
          "y": 393.01
        }
      ]
    },
    {
      "nameRegion": "0",
      "typeRegion": "PENALTY_REGION",
      "coordenates": [
        {
          "x": 122.46,
          "y": 553.51
        },
        {
          "x": 89.75,
          "y": 382.64
        },
        {
          "x": -81.1,
          "y": 415.36
        },
        {
          "x": -48.39,
          "y": 586.22
        }
      ]
    },
    {
      "nameRegion": "1",
      "typeRegion": "PENALTY_REGION",
      "coordenates": [
        {
          "x": 286.66,
          "y": 98.44
        },
        {
          "x": 209.26,
          "y": 64.47
        },
        {
          "x": 175.28,
          "y": 141.87
        },
        {
          "x": 252.69,
          "y": 175.85
        }
      ]
    },
    {
      "nameRegion": "2",
      "typeRegion": "PENALTY_REGION",
      "coordenates": [
        {
          "x": -103.68,
          "y": 75.33
        },
        {
          "x": -325.13,
          "y": -47.92
        },
        {
          "x": -448.39,
          "y": 173.52
        },
        {
          "x": -226.94,
          "y": 296.78
        }
      ]
    },
    {
      "nameRegion": "0",
      "typeRegion": "BONUS_REGION",
      "coordenates": [
        {
          "x": 36.22,
          "y": 8.51
        },
        {
          "x": -14.6,
          "y": -112.16
        },
        {
          "x": -135.28,
          "y": -61.34
        },
        {
          "x": -84.45,
          "y": 59.33
        }
      ]
    },
    {
      "nameRegion": "1",
      "typeRegion": "BONUS_REGION",
      "coordenates": [
        {
          "x": 359.25,
          "y": 35.44
        },
        {
          "x": 276.57,
          "y": 128.55
        },
        {
          "x": 369.68,
          "y": 211.22
        },
        {
          "x": 452.35,
          "y": 118.12
        }
      ]
    },
    {
      "nameRegion": "2",
      "typeRegion": "BONUS_REGION",
      "coordenates": [
        {
          "x": 511.33,
          "y": -384.4
        },
        {
          "x": 351.5,
          "y": -407.67
        },
        {
          "x": 328.23,
          "y": -247.85
        },
        {
          "x": 488.05,
          "y": -224.58
        }
      ]
    },
    {
      "nameRegion": "3",
      "typeRegion": "BONUS_REGION",
      "coordenates": [
        {
          "x": -176.01,
          "y": -108.36
        },
        {
          "x": -230.54,
          "y": -145.43
        },
        {
          "x": -267.61,
          "y": -90.9
        },
        {
          "x": -213.09,
          "y": -53.83
        }
      ]
    },
    {
      "nameRegion": "4",
      "typeRegion": "BONUS_REGION",
      "coordenates": [
        {
          "x": -398.01,
          "y": 297.38
        },
        {
          "x": -467.7,
          "y": 201.24
        },
        {
          "x": -563.84,
          "y": 270.93
        },
        {
          "x": -494.15,
          "y": 367.07
        }
      ]
    }
  ]
}
