{
  "regions": [
    {
      "nameRegion": "0",
      "typeRegion": "NFZ_REGION",
      "coordenates": [
        {
          "x": 33.09,
          "y": -397.94
        },
        {
          "x": 15.27,
          "y": -538.47
        },
        {
          "x": -125.26,
          "y": -520.65
        },
        {
          "x": -107.44,
          "y": -380.11
        }
      ]
    },
    {
      "nameRegion": "1",
      "typeRegion": "NFZ_REGION",
      "coordenates": [
        {
          "x": 89.36,
          "y": -280.5
        },
        {
          "x": 80.4,
          "y": -211.58
        },
        {
          "x": 149.32,
          "y": -202.63
        },
        {
          "x": 158.28,
          "y": -271.55
        }
      ]
    },
    {
      "nameRegion": "2",
      "typeRegion": "NFZ_REGION",
      "coordenates": [
        {
          "x": 266.61,
          "y": -449.52
        },
        {
          "x": 186.32,
          "y": -358.15
        },
        {
          "x": 277.7,
          "y": -277.87
        },
        {
          "x": 357.98,
          "y": -369.24
        }
      ]
    },
    {
      "nameRegion": "3",
      "typeRegion": "NFZ_REGION",
      "coordenates": [
        {
          "x": 268.5,
          "y": 409.18
        },
        {
          "x": 193.22,
          "y": 309.06
        },
        {
          "x": 93.11,
          "y": 384.34
        },
        {
          "x": 168.38,
          "y": 484.45
        }
      ]
    },
    {
      "nameRegion": "4",
      "typeRegion": "NFZ_REGION",
      "coordenates": [
        {
          "x": -56.02,
          "y": 328.11
        },
        {
          "x": -255.45,
          "y": 425.34
        },
        {
          "x": -158.22,
          "y": 624.76
        },
        {
          "x": 41.2,
          "y": 527.53
        }
      ]
    },
    {
      "nameRegion": "5",
      "typeRegion": "NFZ_REGION",
      "coordenates": [
        {
          "x": -139.01,
          "y": -268.46
        },
        {
          "x": -162.7,
          "y": -192.43
        },
        {
          "x": -86.68,
          "y": -168.74
        },
        {
          "x": -62.99,
          "y": -244.77
        }
      ]
    },
    {
      "nameRegion": "6",
      "typeRegion": "NFZ_REGION",
      "coordenates": [
        {
          "x": -400.09,
          "y": 494.26
        },
        {
          "x": -404.94,
          "y": 430.38
        },
        {
          "x": -468.82,
          "y": 435.23
        },
        {
          "x": -463.97,
          "y": 499.11
        }
      ]
    },
    {
      "nameRegion": "7",
      "typeRegion": "NFZ_REGION",
      "coordenates": [
        {
          "x": 440.96,
          "y": 81.84
        },
        {
          "x": 347.99,
          "y": 8.7
        },
        {
          "x": 274.84,
          "y": 101.67
        },
        {
          "x": 367.82,
          "y": 174.82
        }
      ]
    },
    {
      "nameRegion": "8",
      "typeRegion": "NFZ_REGION",
      "coordenates": [
        {
          "x": 581.54,
          "y": -93.46
        },
        {
          "x": 487.8,
          "y": -174.49
        },
        {
          "x": 406.77,
          "y": -80.74
        },
        {
          "x": 500.51,
          "y": 0.28
        }
      ]
    },
    {
      "nameRegion": "9",
      "typeRegion": "NFZ_REGION",
      "coordenates": [
        {
          "x": 445.66,
          "y": 183.55
        },
        {
          "x": 322.48,
          "y": 271.41
        },
        {
          "x": 410.34,
          "y": 394.58
        },
        {
          "x": 533.52,
          "y": 306.72
        }
      ]
    },
    {
      "nameRegion": "0",
      "typeRegion": "PENALTY_REGION",
      "coordenates": [
        {
          "x": -304.77,
          "y": -588.09
        },
        {
          "x": -478.66,
          "y": -438.75
        },
        {
          "x": -329.33,
          "y": -264.86
        },
        {
          "x": -155.43,
          "y": -414.19
        }
      ]
    },
    {
      "nameRegion": "1",
      "typeRegion": "PENALTY_REGION",
      "coordenates": [
        {
          "x": 98.95,
          "y": -132.11
        },
        {
          "x": 21.88,
          "y": -158.24
        },
        {
          "x": -4.24,
          "y": -81.17
        },
        {
          "x": 72.82,
          "y": -55.04
        }
      ]
    },
    {
      "nameRegion": "2",
      "typeRegion": "PENALTY_REGION",
      "coordenates": [
        {
          "x": -132.03,
          "y": -84.85
        },
        {
          "x": -261.71,
          "y": 36.32
        },
        {
          "x": -140.54,
          "y": 166.01
        },
        {
          "x": -10.85,
          "y": 44.83
        }
      ]
    },
    {
      "nameRegion": "3",
      "typeRegion": "PENALTY_REGION",
      "coordenates": [
        {
          "x": 199.94,
          "y": -37.84
        },
        {
          "x": 113.43,
          "y": 42.81
        },
        {
          "x": 194.09,
          "y": 129.33
        },
        {
          "x": 280.61,
          "y": 48.67
        }
      ]
    },
    {
      "nameRegion": "4",
      "typeRegion": "PENALTY_REGION",
      "coordenates": [
        {
          "x": 578.36,
          "y": -456.53
        },
        {
          "x": 477.15,
          "y": -580.16
        },
        {
          "x": 353.52,
          "y": -478.95
        },
        {
          "x": 454.73,
          "y": -355.31
        }
      ]
    },
    {
      "nameRegion": "5",
      "typeRegion": "PENALTY_REGION",
      "coordenates": [
        {
          "x": 301.89,
          "y": -143.97
        },
        {
          "x": 223.27,
          "y": -77.76
        },
        {
          "x": 289.48,
          "y": 0.85
        },
        {
          "x": 368.1,
          "y": -65.35
        }
      ]
    },
    {
      "nameRegion": "6",
      "typeRegion": "PENALTY_REGION",
      "coordenates": [
        {
          "x": -429.51,
          "y": -352.62
        },
        {
          "x": -541.46,
          "y": -365.04
        },
        {
          "x": -553.87,
          "y": -253.09
        },
        {
          "x": -441.92,
          "y": -240.67
        }
      ]
    },
    {
      "nameRegion": "0",
      "typeRegion": "BONUS_REGION",
      "coordenates": [
        {
          "x": -329.09,
          "y": -199.6
        },
        {
          "x": -454.87,
          "y": -107.86
        },
        {
          "x": -363.13,
          "y": 17.91
        },
        {
          "x": -237.35,
          "y": -73.82
        }
      ]
    },
    {
      "nameRegion": "1",
      "typeRegion": "BONUS_REGION",
      "coordenates": [
        {
          "x": -329.31,
          "y": 109.42
        },
        {
          "x": -383.7,
          "y": 23.69
        },
        {
          "x": -469.43,
          "y": 78.08
        },
        {
          "x": -415.04,
          "y": 163.81
        }
      ]
    },
    {
      "nameRegion": "2",
      "typeRegion": "BONUS_REGION",
      "coordenates": [
        {
          "x": -299.88,
          "y": 331.06
        },
        {
          "x": -374.21,
          "y": 389.77
        },
        {
          "x": -315.5,
          "y": 464.1
        },
        {
          "x": -241.17,
          "y": 405.39
        }
      ]
    },
    {
      "nameRegion": "3",
      "typeRegion": "BONUS_REGION",
      "coordenates": [
        {
          "x": -310.26,
          "y": 269.54
        },
        {
          "x": -358.74,
          "y": 168.92
        },
        {
          "x": -459.36,
          "y": 217.4
        },
        {
          "x": -410.88,
          "y": 318.02
        }
      ]
    },
    {
      "nameRegion": "4",
      "typeRegion": "BONUS_REGION",
      "coordenates": [
        {
          "x": -200.02,
          "y": 281.04
        },
        {
          "x": -218.28,
          "y": 219.68
        },
        {
          "x": -279.64,
          "y": 237.94
        },
        {
          "x": -261.38,
          "y": 299.3
        }
      ]
    },
    {
      "nameRegion": "5",
      "typeRegion": "BONUS_REGION",
      "coordenates": [
        {
          "x": 48.87,
          "y": -178.61
        },
        {
          "x": 48.74,
          "y": -250.19
        },
        {
          "x": -22.84,
          "y": -250.06
        },
        {
          "x": -22.7,
          "y": -178.47
        }
      ]
    },
    {
      "nameRegion": "6",
      "typeRegion": "BONUS_REGION",
      "coordenates": [
        {
          "x": 99.79,
          "y": 103.69
        },
        {
          "x": 33.39,
          "y": 216.37
        },
        {
          "x": 146.08,
          "y": 282.77
        },
        {
          "x": 212.48,
          "y": 170.09
        }
      ]
    },
    {
      "nameRegion": "7",
      "typeRegion": "BONUS_REGION",
      "coordenates": [
        {
          "x": 84.34,
          "y": -316.2
        },
        {
          "x": 38.79,
          "y": -391.7
        },
        {
          "x": -36.7,
          "y": -346.16
        },
        {
          "x": 8.83,
          "y": -270.65
        }
      ]
    },
    {
      "nameRegion": "8",
      "typeRegion": "BONUS_REGION",
      "coordenates": [
        {
          "x": 314.91,
          "y": 367.5
        },
        {
          "x": 241.51,
          "y": 485.78
        },
        {
          "x": 359.79,
          "y": 559.18
        },
        {
          "x": 433.19,
          "y": 440.9
        }
      ]
    },
    {
      "nameRegion": "9",
      "typeRegion": "BONUS_REGION",
      "coordenates": [
        {
          "x": 264.24,
          "y": -176.41
        },
        {
          "x": 214.19,
          "y": -185.04
        },
        {
          "x": 205.55,
          "y": -134.99
        },
        {
          "x": 255.6,
          "y": -126.36
        }
      ]
    },
    {
      "nameRegion": "10",
      "typeRegion": "BONUS_REGION",
      "coordenates": [
        {
          "x": 183.97,
          "y": -196.97
        },
        {
          "x": 121.85,
          "y": -203.95
        },
        {
          "x": 114.86,
          "y": -141.83
        },
        {
          "x": 176.99,
          "y": -134.85
        }
      ]
    },
    {
      "nameRegion": "11",
      "typeRegion": "BONUS_REGION",
      "coordenates": [
        {
          "x": -71.25,
          "y": -346.18
        },
        {
          "x": -107.08,
          "y": -307.62
        },
        {
          "x": -68.52,
          "y": -271.79
        },
        {
          "x": -32.69,
          "y": -310.36
        }
      ]
    },
    {
      "nameRegion": "12",
      "typeRegion": "BONUS_REGION",
      "coordenates": [
        {
          "x": 526.93,
          "y": -280.28
        },
        {
          "x": 478.43,
          "y": -350.18
        },
        {
          "x": 408.54,
          "y": -301.68
        },
        {
          "x": 457.03,
          "y": -231.79
        }
      ]
    },
    {
      "nameRegion": "13",
      "typeRegion": "BONUS_REGION",
      "coordenates": [
        {
          "x": 243.54,
          "y": -530.16
        },
        {
          "x": 190.66,
          "y": -515.16
        },
        {
          "x": 205.66,
          "y": -462.28
        },
        {
          "x": 258.54,
          "y": -477.28
        }
      ]
    },
    {
      "nameRegion": "14",
      "typeRegion": "BONUS_REGION",
      "coordenates": [
        {
          "x": -523.04,
          "y": -71.68
        },
        {
          "x": -523.37,
          "y": -6.98
        },
        {
          "x": -458.67,
          "y": -6.64
        },
        {
          "x": -458.34,
          "y": -71.35
        }
      ]
    },
    {
      "nameRegion": "15",
      "typeRegion": "BONUS_REGION",
      "coordenates": [
        {
          "x": -2.19,
          "y": 52.14
        },
        {
          "x": -31.15,
          "y": 130.0
        },
        {
          "x": 46.71,
          "y": 158.95
        },
        {
          "x": 75.66,
          "y": 81.09
        }
      ]
    },
    {
      "nameRegion": "16",
      "typeRegion": "BONUS_REGION",
      "coordenates": [
        {
          "x": -154.95,
          "y": 188.41
        },
        {
          "x": -175.81,
          "y": 149.87
        },
        {
          "x": -214.35,
          "y": 170.73
        },
        {
          "x": -193.49,
          "y": 209.27
        }
      ]
    },
    {
      "nameRegion": "17",
      "typeRegion": "BONUS_REGION",
      "coordenates": [
        {
          "x": -441.58,
          "y": -164.61
        },
        {
          "x": -525.21,
          "y": -185.17
        },
        {
          "x": -545.78,
          "y": -101.54
        },
        {
          "x": -462.15,
          "y": -80.97
        }
      ]
    },
    {
      "nameRegion": "18",
      "typeRegion": "BONUS_REGION",
      "coordenates": [
        {
          "x": -75.62,
          "y": -112.84
        },
        {
          "x": -86.54,
          "y": -66.01
        },
        {
          "x": -39.7,
          "y": -55.1
        },
        {
          "x": -28.79,
          "y": -101.93
        }
      ]
    },
    {
      "nameRegion": "19",
      "typeRegion": "BONUS_REGION",
      "coordenates": [
        {
          "x": -65.8,
          "y": 151.54
        },
        {
          "x": -136.46,
          "y": 167.43
        },
        {
          "x": -120.57,
          "y": 238.09
        },
        {
          "x": -49.91,
          "y": 222.2
        }
      ]
    },
    {
      "nameRegion": "20",
      "typeRegion": "BONUS_REGION",
      "coordenates": [
        {
          "x": 88.07,
          "y": 385.5
        },
        {
          "x": 10.35,
          "y": 447.95
        },
        {
          "x": 72.8,
          "y": 525.67
        },
        {
          "x": 150.52,
          "y": 463.22
        }
      ]
    },
    {
      "nameRegion": "21",
      "typeRegion": "BONUS_REGION",
      "coordenates": [
        {
          "x": 121.38,
          "y": -466.95
        },
        {
          "x": 99.23,
          "y": -383.21
        },
        {
          "x": 182.97,
          "y": -361.05
        },
        {
          "x": 205.12,
          "y": -444.8
        }
      ]
    },
    {
      "nameRegion": "22",
      "typeRegion": "BONUS_REGION",
      "coordenates": [
        {
          "x": 61.72,
          "y": -10.83
        },
        {
          "x": 0.68,
          "y": -15.29
        },
        {
          "x": -3.77,
          "y": 45.75
        },
        {
          "x": 57.26,
          "y": 50.21
        }
      ]
    },
    {
      "nameRegion": "23",
      "typeRegion": "BONUS_REGION",
      "coordenates": [
        {
          "x": -200.85,
          "y": -148.91
        },
        {
          "x": -224.04,
          "y": -181.08
        },
        {
          "x": -256.21,
          "y": -157.89
        },
        {
          "x": -233.02,
          "y": -125.72
        }
      ]
    }
  ]
}
