{
  "regions": [
    {
      "nameRegion": "0",
      "typeRegion": "NFZ_REGION",
      "coordenates": [
        {
          "x": -135.51,
          "y": -451.53
        },
        {
          "x": -199.67,
          "y": -452.09
        },
        {
          "x": -200.22,
          "y": -387.94
        },
        {
          "x": -136.07,
          "y": -387.38
        }
      ]
    },
    {
      "nameRegion": "1",
      "typeRegion": "NFZ_REGION",
      "coordenates": [
        {
          "x": 181.88,
          "y": 209.91
        },
        {
          "x": -49.33,
          "y": 334.7
        },
        {
          "x": 75.45,
          "y": 565.91
        },
        {
          "x": 306.67,
          "y": 441.12
        }
      ]
    },
    {
      "nameRegion": "2",
      "typeRegion": "NFZ_REGION",
      "coordenates": [
        {
          "x": 43.1,
          "y": -347.37
        },
        {
          "x": -18.32,
          "y": -227.74
        },
        {
          "x": 101.3,
          "y": -166.31
        },
        {
          "x": 162.73,
          "y": -285.94
        }
      ]
    },
    {
      "nameRegion": "3",
      "typeRegion": "NFZ_REGION",
      "coordenates": [
        {
          "x": 119.11,
          "y": 93.68
        },
        {
          "x": 77.35,
          "y": 168.47
        },
        {
          "x": 152.14,
          "y": 210.23
        },
        {
          "x": 193.9,
          "y": 135.44
        }
      ]
    },
    {
      "nameRegion": "4",
      "typeRegion": "NFZ_REGION",
      "coordenates": [
        {
          "x": -177.66,
          "y": 135.64
        },
        {
          "x": -185.59,
          "y": 8.23
        },
        {
          "x": -312.99,
          "y": 16.16
        },
        {
          "x": -305.07,
          "y": 143.56
        }
      ]
    },
    {
      "nameRegion": "5",
      "typeRegion": "NFZ_REGION",
      "coordenates": [
        {
          "x": 469.54,
          "y": 165.24
        },
        {
          "x": 263.67,
          "y": 200.7
        },
        {
          "x": 299.12,
          "y": 406.57
        },
        {
          "x": 504.99,
          "y": 371.11
        }
      ]
    },
    {
      "nameRegion": "0",
      "typeRegion": "PENALTY_REGION",
      "coordenates": [
        {
          "x": 533.22,
          "y": -541.33
        },
        {
          "x": 382.01,
          "y": -580.79
        },
        {
          "x": 342.55,
          "y": -429.57
        },
        {
          "x": 493.77,
          "y": -390.11
        }
      ]
    },
    {
      "nameRegion": "1",
      "typeRegion": "PENALTY_REGION",
      "coordenates": [
        {
          "x": -368.88,
          "y": -552.59
        },
        {
          "x": -423.61,
          "y": -408.63
        },
        {
          "x": -279.66,
          "y": -353.9
        },
        {
          "x": -224.92,
          "y": -497.85
        }
      ]
    },
    {
      "nameRegion": "2",
      "typeRegion": "PENALTY_REGION",
      "coordenates": [
        {
          "x": 477.08,
          "y": -73.1
        },
        {
          "x": 386.95,
          "y": -265.62
        },
        {
          "x": 194.43,
          "y": -175.5
        },
        {
          "x": 284.55,
          "y": 17.01
        }
      ]
    },
    {
      "nameRegion": "3",
      "typeRegion": "PENALTY_REGION",
      "coordenates": [
        {
          "x": 68.74,
          "y": 3.99
        },
        {
          "x": -67.08,
          "y": -24.07
        },
        {
          "x": -95.15,
          "y": 111.75
        },
        {
          "x": 40.67,
          "y": 139.82
        }
      ]
    },
    {
      "nameRegion": "4",
      "typeRegion": "PENALTY_REGION",
      "coordenates": [
        {
          "x": -450.24,
          "y": 337.27
        },
        {
          "x": -593.3,
          "y": 402.54
        },
        {
          "x": -528.03,
          "y": 545.6
        },
        {
          "x": -384.97,
          "y": 480.32
        }
      ]
    },
    {
      "nameRegion": "5",
      "typeRegion": "PENALTY_REGION",
      "coordenates": [
        {
          "x": -360.11,
          "y": 97.51
        },
        {
          "x": -436.78,
          "y": -41.92
        },
        {
          "x": -576.22,
          "y": 34.73
        },
        {
          "x": -499.56,
          "y": 174.17
        }
      ]
    },
    {
      "nameRegion": "0",
      "typeRegion": "BONUS_REGION",
      "coordenates": [
        {
          "x": -238.59,
          "y": 154.07
        },
        {
          "x": -357.49,
          "y": 360.6
        },
        {
          "x": -150.95,
          "y": 479.5
        },
        {
          "x": -32.05,
          "y": 272.96
        }
      ]
    },
    {
      "nameRegion": "1",
      "typeRegion": "BONUS_REGION",
      "coordenates": [
        {
          "x": -474.87,
          "y": -322.23
        },
        {
          "x": -488.76,
          "y": -137.46
        },
        {
          "x": -303.99,
          "y": -123.58
        },
        {
          "x": -290.1,
          "y": -308.34
        }
      ]
    },
    {
      "nameRegion": "2",
      "typeRegion": "BONUS_REGION",
      "coordenates": [
        {
          "x": 188.68,
          "y": -403.96
        },
        {
          "x": 119.34,
          "y": -386.99
        },
        {
          "x": 136.31,
          "y": -317.65
        },
        {
          "x": 205.65,
          "y": -334.62
        }
      ]
    },
    {
      "nameRegion": "3",
      "typeRegion": "BONUS_REGION",
      "coordenates": [
        {
          "x": 449.41,
          "y": 141.74
        },
        {
          "x": 447.69,
          "y": 24.98
        },
        {
          "x": 330.94,
          "y": 26.69
        },
        {
          "x": 332.65,
          "y": 143.45
        }
      ]
    },
    {
      "nameRegion": "4",
      "typeRegion": "BONUS_REGION",
      "coordenates": [
        {
          "x": 529.89,
          "y": 384.63
        },
        {
          "x": 377.5,
          "y": 414.6
        },
        {
          "x": 407.48,
          "y": 566.99
        },
        {
          "x": 559.86,
          "y": 537.02
        }
      ]
    },
    {
      "nameRegion": "5",
      "typeRegion": "BONUS_REGION",
      "coordenates": [
        {
          "x": -332.0,
          "y": 112.95
        },
        {
          "x": -367.17,
          "y": 143.8
        },
        {
          "x": -336.32,
          "y": 178.97
        },
        {
          "x": -301.15,
          "y": 148.12
        }
      ]
    },
    {
      "nameRegion": "6",
      "typeRegion": "BONUS_REGION",
      "coordenates": [
        {
          "x": 270.73,
          "y": -506.59
        },
        {
          "x": 205.35,
          "y": -504.9
        },
        {
          "x": 207.03,
          "y": -439.52
        },
        {
          "x": 272.41,
          "y": -441.21
        }
      ]
    },
    {
      "nameRegion": "7",
      "typeRegion": "BONUS_REGION",
      "coordenates": [
        {
          "x": 10.87,
          "y": -155.87
        },
        {
          "x": -115.63,
          "y": -263.16
        },
        {
          "x": -222.91,
          "y": -136.65
        },
        {
          "x": -96.41,
          "y": -29.36
        }
      ]
    },
    {
      "nameRegion": "8",
      "typeRegion": "BONUS_REGION",
      "coordenates": [
        {
          "x": 162.93,
          "y": -99.54
        },
        {
          "x": 132.25,
          "y": -128.21
        },
        {
          "x": 103.58,
          "y": -97.53
        },
        {
          "x": 134.26,
          "y": -68.86
        }
      ]
    },
    {
      "nameRegion": "9",
      "typeRegion": "BONUS_REGION",
      "coordenates": [
        {
          "x": 57.82,
          "y": -389.47
        },
        {
          "x": -13.03,
          "y": -500.48
        },
        {
          "x": -124.04,
          "y": -429.62
        },
        {
          "x": -53.18,
          "y": -318.61
        }
      ]
    }
  ]
}
