<uav.map.converter.map.Map>
  <regions>
    <uav.map.converter.map.Poly2D>
      <nameRegion>0</nameRegion>
      <typeRegion>NFZ_REGION</typeRegion>
      <coordenates>
        <uav.map.converter.map.Point2D>
          <x>-393.91</x>
          <y>-73.49</y>
        </uav.map.converter.map.Point2D>
        <uav.map.converter.map.Point2D>
          <x>-463.8</x>
          <y>108.4</y>
        </uav.map.converter.map.Point2D>
        <uav.map.converter.map.Point2D>
          <x>-281.91</x>
          <y>178.29</y>
        </uav.map.converter.map.Point2D>
        <uav.map.converter.map.Point2D>
          <x>-212.01</x>
          <y>-3.59</y>
        </uav.map.converter.map.Point2D>
      </coordenates>
    </uav.map.converter.map.Poly2D>
    <uav.map.converter.map.Poly2D>
      <nameRegion>1</nameRegion>
      <typeRegion>NFZ_REGION</typeRegion>
      <coordenates>
        <uav.map.converter.map.Point2D>
          <x>-118.1</x>
          <y>-242.84</y>
        </uav.map.converter.map.Point2D>
        <uav.map.converter.map.Point2D>
          <x>-300.29</x>
          <y>-214.94</y>
        </uav.map.converter.map.Point2D>
        <uav.map.converter.map.Point2D>
          <x>-272.39</x>
          <y>-32.74</y>
        </uav.map.converter.map.Point2D>
        <uav.map.converter.map.Point2D>
          <x>-90.2</x>
          <y>-60.64</y>
        </uav.map.converter.map.Point2D>
      </coordenates>
    </uav.map.converter.map.Poly2D>
    <uav.map.converter.map.Poly2D>
      <nameRegion>2</nameRegion>
      <typeRegion>NFZ_REGION</typeRegion>
      <coordenates>
        <uav.map.converter.map.Point2D>
          <x>114.1</x>
          <y>-446.8</y>
        </uav.map.converter.map.Point2D>
        <uav.map.converter.map.Point2D>
          <x>11.46</x>
          <y>-233.63</y>
        </uav.map.converter.map.Point2D>
        <uav.map.converter.map.Point2D>
          <x>224.63</x>
          <y>-130.98</y>
        </uav.map.converter.map.Point2D>
        <uav.map.converter.map.Point2D>
          <x>327.27</x>
          <y>-344.16</y>
        </uav.map.converter.map.Point2D>
      </coordenates>
    </uav.map.converter.map.Poly2D>
    <uav.map.converter.map.Poly2D>
      <nameRegion>0</nameRegion>
      <typeRegion>PENALTY_REGION</typeRegion>
      <coordenates>
        <uav.map.converter.map.Point2D>
          <x>163.64</x>
          <y>-142.45</y>
        </uav.map.converter.map.Point2D>
        <uav.map.converter.map.Point2D>
          <x>65.6</x>
          <y>-52.79</y>
        </uav.map.converter.map.Point2D>
        <uav.map.converter.map.Point2D>
          <x>155.26</x>
          <y>45.24</y>
        </uav.map.converter.map.Point2D>
        <uav.map.converter.map.Point2D>
          <x>253.3</x>
          <y>-44.41</y>
        </uav.map.converter.map.Point2D>
      </coordenates>
    </uav.map.converter.map.Poly2D>
    <uav.map.converter.map.Poly2D>
      <nameRegion>1</nameRegion>
      <typeRegion>PENALTY_REGION</typeRegion>
      <coordenates>
        <uav.map.converter.map.Point2D>
          <x>160.87</x>
          <y>202.05</y>
        </uav.map.converter.map.Point2D>
        <uav.map.converter.map.Point2D>
          <x>44.79</x>
          <y>310.76</y>
        </uav.map.converter.map.Point2D>
        <uav.map.converter.map.Point2D>
          <x>153.5</x>
          <y>426.84</y>
        </uav.map.converter.map.Point2D>
        <uav.map.converter.map.Point2D>
          <x>269.57</x>
          <y>318.13</y>
        </uav.map.converter.map.Point2D>
      </coordenates>
    </uav.map.converter.map.Poly2D>
    <uav.map.converter.map.Poly2D>
      <nameRegion>2</nameRegion>
      <typeRegion>PENALTY_REGION</typeRegion>
      <coordenates>
        <uav.map.converter.map.Point2D>
          <x>436.66</x>
          <y>-151.74</y>
        </uav.map.converter.map.Point2D>
        <uav.map.converter.map.Point2D>
          <x>332.58</x>
          <y>-225.82</y>
        </uav.map.converter.map.Point2D>
        <uav.map.converter.map.Point2D>
          <x>258.5</x>
          <y>-121.75</y>
        </uav.map.converter.map.Point2D>
        <uav.map.converter.map.Point2D>
          <x>362.57</x>
          <y>-47.66</y>
        </uav.map.converter.map.Point2D>
      </coordenates>
    </uav.map.converter.map.Poly2D>
    <uav.map.converter.map.Poly2D>
      <nameRegion>3</nameRegion>
      <typeRegion>PENALTY_REGION</typeRegion>
      <coordenates>
        <uav.map.converter.map.Point2D>
          <x>-307.33</x>
          <y>306.99</y>
        </uav.map.converter.map.Point2D>
        <uav.map.converter.map.Point2D>
          <x>-357.91</x>
          <y>499.22</y>
        </uav.map.converter.map.Point2D>
        <uav.map.converter.map.Point2D>
          <x>-165.67</x>
          <y>549.8</y>
        </uav.map.converter.map.Point2D>
        <uav.map.converter.map.Point2D>
          <x>-115.1</x>
          <y>357.56</y>
        </uav.map.converter.map.Point2D>
      </coordenates>
    </uav.map.converter.map.Poly2D>
    <uav.map.converter.map.Poly2D>
      <nameRegion>0</nameRegion>
      <typeRegion>BONUS_REGION</typeRegion>
      <coordenates>
        <uav.map.converter.map.Point2D>
          <x>-49.82</x>
          <y>-406.13</y>
        </uav.map.converter.map.Point2D>
        <uav.map.converter.map.Point2D>
          <x>-61.36</x>
          <y>-576.59</y>
        </uav.map.converter.map.Point2D>
        <uav.map.converter.map.Point2D>
          <x>-231.82</x>
          <y>-565.05</y>
        </uav.map.converter.map.Point2D>
        <uav.map.converter.map.Point2D>
          <x>-220.28</x>
          <y>-394.58</y>
        </uav.map.converter.map.Point2D>
      </coordenates>
    </uav.map.converter.map.Poly2D>
  </regions>
</uav.map.converter.map.Map>