{
  "regions": [
    {
      "nameRegion": "0",
      "typeRegion": "NFZ_REGION",
      "coordenates": [
        {
          "x": -137.79,
          "y": -233.3
        },
        {
          "x": -229.65,
          "y": -386.96
        },
        {
          "x": -383.3,
          "y": -295.1
        },
        {
          "x": -291.44,
          "y": -141.45
        }
      ]
    },
    {
      "nameRegion": "1",
      "typeRegion": "NFZ_REGION",
      "coordenates": [
        {
          "x": 442.76,
          "y": 334.51
        },
        {
          "x": 409.59,
          "y": 196.83
        },
        {
          "x": 271.91,
          "y": 230.0
        },
        {
          "x": 305.08,
          "y": 367.68
        }
      ]
    },
    {
      "nameRegion": "2",
      "typeRegion": "NFZ_REGION",
      "coordenates": [
        {
          "x": 143.73,
          "y": 394.29
        },
        {
          "x": 46.44,
          "y": 233.93
        },
        {
          "x": -113.92,
          "y": 331.21
        },
        {
          "x": -16.63,
          "y": 491.58
        }
      ]
    },
    {
      "nameRegion": "3",
      "typeRegion": "NFZ_REGION",
      "coordenates": [
        {
          "x": -363.13,
          "y": 6.58
        },
        {
          "x": -433.54,
          "y": 199.08
        },
        {
          "x": -241.04,
          "y": 269.49
        },
        {
          "x": -170.63,
          "y": 76.99
        }
      ]
    },
    {
      "nameRegion": "4",
      "typeRegion": "NFZ_REGION",
      "coordenates": [
        {
          "x": 226.81,
          "y": -412.31
        },
        {
          "x": 195.46,
          "y": -496.37
        },
        {
          "x": 111.39,
          "y": -465.01
        },
        {
          "x": 142.75,
          "y": -380.95
        }
      ]
    },
    {
      "nameRegion": "5",
      "typeRegion": "NFZ_REGION",
      "coordenates": [
        {
          "x": 429.15,
          "y": -90.19
        },
        {
          "x": 360.41,
          "y": -194.94
        },
        {
          "x": 255.65,
          "y": -126.2
        },
        {
          "x": 324.39,
          "y": -21.44
        }
      ]
    },
    {
      "nameRegion": "6",
      "typeRegion": "NFZ_REGION",
      "coordenates": [
        {
          "x": 132.75,
          "y": 197.13
        },
        {
          "x": 123.66,
          "y": 258.69
        },
        {
          "x": 185.21,
          "y": 267.78
        },
        {
          "x": 194.3,
          "y": 206.22
        }
      ]
    },
    {
      "nameRegion": "7",
      "typeRegion": "NFZ_REGION",
      "coordenates": [
        {
          "x": -467.81,
          "y": 229.66
        },
        {
          "x": -565.56,
          "y": 333.05
        },
        {
          "x": -462.17,
          "y": 430.8
        },
        {
          "x": -364.42,
          "y": 327.41
        }
      ]
    },
    {
      "nameRegion": "8",
      "typeRegion": "NFZ_REGION",
      "coordenates": [
        {
          "x": 498.77,
          "y": -32.9
        },
        {
          "x": 383.27,
          "y": 75.67
        },
        {
          "x": 491.86,
          "y": 191.17
        },
        {
          "x": 607.36,
          "y": 82.59
        }
      ]
    },
    {
      "nameRegion": "9",
      "typeRegion": "NFZ_REGION",
      "coordenates": [
        {
          "x": -482.4,
          "y": -304.96
        },
        {
          "x": -535.98,
          "y": -206.68
        },
        {
          "x": -437.7,
          "y": -153.1
        },
        {
          "x": -384.12,
          "y": -251.38
        }
      ]
    },
    {
      "nameRegion": "10",
      "typeRegion": "NFZ_REGION",
      "coordenates": [
        {
          "x": -32.29,
          "y": -455.9
        },
        {
          "x": -71.25,
          "y": -313.38
        },
        {
          "x": 71.26,
          "y": -274.42
        },
        {
          "x": 110.21,
          "y": -416.94
        }
      ]
    },
    {
      "nameRegion": "11",
      "typeRegion": "NFZ_REGION",
      "coordenates": [
        {
          "x": -351.28,
          "y": 338.02
        },
        {
          "x": -388.17,
          "y": 472.86
        },
        {
          "x": -253.32,
          "y": 509.75
        },
        {
          "x": -216.43,
          "y": 374.91
        }
      ]
    },
    {
      "nameRegion": "0",
      "typeRegion": "PENALTY_REGION",
      "coordenates": [
        {
          "x": -110.17,
          "y": -139.46
        },
        {
          "x": -112.51,
          "y": 35.34
        },
        {
          "x": 62.3,
          "y": 37.68
        },
        {
          "x": 64.64,
          "y": -137.13
        }
      ]
    },
    {
      "nameRegion": "1",
      "typeRegion": "PENALTY_REGION",
      "coordenates": [
        {
          "x": 519.65,
          "y": -259.6
        },
        {
          "x": 409.2,
          "y": -199.96
        },
        {
          "x": 468.84,
          "y": -89.51
        },
        {
          "x": 579.29,
          "y": -149.15
        }
      ]
    },
    {
      "nameRegion": "2",
      "typeRegion": "PENALTY_REGION",
      "coordenates": [
        {
          "x": 245.42,
          "y": 85.29
        },
        {
          "x": 186.89,
          "y": 111.54
        },
        {
          "x": 213.14,
          "y": 170.06
        },
        {
          "x": 271.67,
          "y": 143.81
        }
      ]
    },
    {
      "nameRegion": "3",
      "typeRegion": "PENALTY_REGION",
      "coordenates": [
        {
          "x": 451.96,
          "y": -561.84
        },
        {
          "x": 392.0,
          "y": -459.84
        },
        {
          "x": 494.0,
          "y": -399.87
        },
        {
          "x": 553.96,
          "y": -501.88
        }
      ]
    },
    {
      "nameRegion": "4",
      "typeRegion": "PENALTY_REGION",
      "coordenates": [
        {
          "x": 38.9,
          "y": 143.65
        },
        {
          "x": 2.4,
          "y": 155.88
        },
        {
          "x": 14.63,
          "y": 192.39
        },
        {
          "x": 51.13,
          "y": 180.16
        }
      ]
    },
    {
      "nameRegion": "5",
      "typeRegion": "PENALTY_REGION",
      "coordenates": [
        {
          "x": 418.72,
          "y": -294.6
        },
        {
          "x": 383.68,
          "y": -384.21
        },
        {
          "x": 294.08,
          "y": -349.17
        },
        {
          "x": 329.11,
          "y": -259.57
        }
      ]
    },
    {
      "nameRegion": "6",
      "typeRegion": "PENALTY_REGION",
      "coordenates": [
        {
          "x": 345.14,
          "y": 423.8
        },
        {
          "x": 324.78,
          "y": 514.24
        },
        {
          "x": 415.21,
          "y": 534.59
        },
        {
          "x": 435.57,
          "y": 444.16
        }
      ]
    },
    {
      "nameRegion": "7",
      "typeRegion": "PENALTY_REGION",
      "coordenates": [
        {
          "x": 319.56,
          "y": -411.15
        },
        {
          "x": 256.46,
          "y": -454.19
        },
        {
          "x": 213.42,
          "y": -391.09
        },
        {
          "x": 276.52,
          "y": -348.05
        }
      ]
    },
    {
      "nameRegion": "8",
      "typeRegion": "PENALTY_REGION",
      "coordenates": [
        {
          "x": -143.74,
          "y": -487.89
        },
        {
          "x": -237.14,
          "y": -453.57
        },
        {
          "x": -202.82,
          "y": -360.17
        },
        {
          "x": -109.42,
          "y": -394.49
        }
      ]
    },
    {
      "nameRegion": "9",
      "typeRegion": "PENALTY_REGION",
      "coordenates": [
        {
          "x": -388.29,
          "y": -130.65
        },
        {
          "x": -498.26,
          "y": -151.18
        },
        {
          "x": -518.79,
          "y": -41.21
        },
        {
          "x": -408.82,
          "y": -20.68
        }
      ]
    },
    {
      "nameRegion": "10",
      "typeRegion": "PENALTY_REGION",
      "coordenates": [
        {
          "x": -240.64,
          "y": -121.7
        },
        {
          "x": -349.17,
          "y": -142.21
        },
        {
          "x": -369.69,
          "y": -33.68
        },
        {
          "x": -261.15,
          "y": -13.16
        }
      ]
    },
    {
      "nameRegion": "11",
      "typeRegion": "PENALTY_REGION",
      "coordenates": [
        {
          "x": -432.26,
          "y": -349.89
        },
        {
          "x": -463.71,
          "y": -440.3
        },
        {
          "x": -554.12,
          "y": -408.85
        },
        {
          "x": -522.67,
          "y": -318.44
        }
      ]
    },
    {
      "nameRegion": "12",
      "typeRegion": "PENALTY_REGION",
      "coordenates": [
        {
          "x": -382.55,
          "y": -603.8
        },
        {
          "x": -481.57,
          "y": -474.55
        },
        {
          "x": -352.32,
          "y": -375.53
        },
        {
          "x": -253.3,
          "y": -504.78
        }
      ]
    },
    {
      "nameRegion": "0",
      "typeRegion": "BONUS_REGION",
      "coordenates": [
        {
          "x": 211.77,
          "y": -276.68
        },
        {
          "x": 56.28,
          "y": -254.05
        },
        {
          "x": 78.9,
          "y": -98.56
        },
        {
          "x": 234.39,
          "y": -121.18
        }
      ]
    },
    {
      "nameRegion": "1",
      "typeRegion": "BONUS_REGION",
      "coordenates": [
        {
          "x": 297.19,
          "y": -562.18
        },
        {
          "x": 262.97,
          "y": -456.51
        },
        {
          "x": 368.65,
          "y": -422.29
        },
        {
          "x": 402.86,
          "y": -527.97
        }
      ]
    },
    {
      "nameRegion": "2",
      "typeRegion": "BONUS_REGION",
      "coordenates": [
        {
          "x": 63.36,
          "y": 48.2
        },
        {
          "x": 53.17,
          "y": 122.86
        },
        {
          "x": 127.83,
          "y": 133.05
        },
        {
          "x": 138.02,
          "y": 58.39
        }
      ]
    },
    {
      "nameRegion": "3",
      "typeRegion": "BONUS_REGION",
      "coordenates": [
        {
          "x": 310.53,
          "y": 490.67
        },
        {
          "x": 212.11,
          "y": 360.05
        },
        {
          "x": 81.49,
          "y": 458.48
        },
        {
          "x": 179.92,
          "y": 589.09
        }
      ]
    },
    {
      "nameRegion": "4",
      "typeRegion": "BONUS_REGION",
      "coordenates": [
        {
          "x": 266.17,
          "y": 18.88
        },
        {
          "x": 238.28,
          "y": 62.54
        },
        {
          "x": 281.94,
          "y": 90.43
        },
        {
          "x": 309.83,
          "y": 46.77
        }
      ]
    },
    {
      "nameRegion": "5",
      "typeRegion": "BONUS_REGION",
      "coordenates": [
        {
          "x": 492.92,
          "y": 445.55
        },
        {
          "x": 451.33,
          "y": 470.5
        },
        {
          "x": 476.28,
          "y": 512.09
        },
        {
          "x": 517.86,
          "y": 487.14
        }
      ]
    },
    {
      "nameRegion": "6",
      "typeRegion": "BONUS_REGION",
      "coordenates": [
        {
          "x": -105.95,
          "y": 409.46
        },
        {
          "x": -192.96,
          "y": 416.0
        },
        {
          "x": -186.42,
          "y": 503.01
        },
        {
          "x": -99.41,
          "y": 496.47
        }
      ]
    },
    {
      "nameRegion": "7",
      "typeRegion": "BONUS_REGION",
      "coordenates": [
        {
          "x": -149.26,
          "y": 63.79
        },
        {
          "x": -156.49,
          "y": 144.33
        },
        {
          "x": -75.94,
          "y": 151.57
        },
        {
          "x": -68.71,
          "y": 71.02
        }
      ]
    }
  ]
}
