{
  "regions": [
    {
      "nameRegion": "0",
      "typeRegion": "NFZ_REGION",
      "coordenates": [
        {
          "x": 180.27,
          "y": -317.9
        },
        {
          "x": 156.96,
          "y": -115.03
        },
        {
          "x": 359.82,
          "y": -91.72
        },
        {
          "x": 383.14,
          "y": -294.58
        }
      ]
    },
    {
      "nameRegion": "1",
      "typeRegion": "NFZ_REGION",
      "coordenates": [
        {
          "x": -272.78,
          "y": 226.99
        },
        {
          "x": -398.07,
          "y": 347.39
        },
        {
          "x": -277.67,
          "y": 472.67
        },
        {
          "x": -152.38,
          "y": 352.27
        }
      ]
    },
    {
      "nameRegion": "2",
      "typeRegion": "NFZ_REGION",
      "coordenates": [
        {
          "x": 86.64,
          "y": 267.22
        },
        {
          "x": -24.98,
          "y": 318.72
        },
        {
          "x": 26.51,
          "y": 430.34
        },
        {
          "x": 138.13,
          "y": 378.85
        }
      ]
    },
    {
      "nameRegion": "3",
      "typeRegion": "NFZ_REGION",
      "coordenates": [
        {
          "x": 293.94,
          "y": 241.64
        },
        {
          "x": 187.0,
          "y": 213.44
        },
        {
          "x": 158.8,
          "y": 320.37
        },
        {
          "x": 265.73,
          "y": 348.58
        }
      ]
    },
    {
      "nameRegion": "4",
      "typeRegion": "NFZ_REGION",
      "coordenates": [
        {
          "x": -50.28,
          "y": -349.75
        },
        {
          "x": -238.5,
          "y": -374.07
        },
        {
          "x": -262.82,
          "y": -185.85
        },
        {
          "x": -74.6,
          "y": -161.53
        }
      ]
    },
    {
      "nameRegion": "5",
      "typeRegion": "NFZ_REGION",
      "coordenates": [
        {
          "x": -503.26,
          "y": 93.17
        },
        {
          "x": -607.51,
          "y": 228.72
        },
        {
          "x": -471.96,
          "y": 332.98
        },
        {
          "x": -367.71,
          "y": 197.42
        }
      ]
    },
    {
      "nameRegion": "6",
      "typeRegion": "NFZ_REGION",
      "coordenates": [
        {
          "x": 508.22,
          "y": 276.42
        },
        {
          "x": 327.8,
          "y": 301.57
        },
        {
          "x": 352.95,
          "y": 481.99
        },
        {
          "x": 533.37,
          "y": 456.84
        }
      ]
    },
    {
      "nameRegion": "7",
      "typeRegion": "NFZ_REGION",
      "coordenates": [
        {
          "x": 281.68,
          "y": -4.8
        },
        {
          "x": 133.5,
          "y": 43.6
        },
        {
          "x": 181.91,
          "y": 191.79
        },
        {
          "x": 330.09,
          "y": 143.37
        }
      ]
    },
    {
      "nameRegion": "8",
      "typeRegion": "NFZ_REGION",
      "coordenates": [
        {
          "x": -503.03,
          "y": -198.42
        },
        {
          "x": -575.93,
          "y": 9.01
        },
        {
          "x": -368.5,
          "y": 81.91
        },
        {
          "x": -295.59,
          "y": -125.51
        }
      ]
    },
    {
      "nameRegion": "0",
      "typeRegion": "PENALTY_REGION",
      "coordenates": [
        {
          "x": 79.52,
          "y": 443.08
        },
        {
          "x": 5.13,
          "y": 428.64
        },
        {
          "x": -9.3,
          "y": 503.03
        },
        {
          "x": 65.08,
          "y": 517.47
        }
      ]
    },
    {
      "nameRegion": "1",
      "typeRegion": "PENALTY_REGION",
      "coordenates": [
        {
          "x": -340.74,
          "y": -564.68
        },
        {
          "x": -452.78,
          "y": -460.25
        },
        {
          "x": -348.35,
          "y": -348.22
        },
        {
          "x": -236.32,
          "y": -452.65
        }
      ]
    },
    {
      "nameRegion": "2",
      "typeRegion": "PENALTY_REGION",
      "coordenates": [
        {
          "x": 529.98,
          "y": 3.78
        },
        {
          "x": 406.09,
          "y": -8.79
        },
        {
          "x": 393.51,
          "y": 115.09
        },
        {
          "x": 517.4,
          "y": 127.67
        }
      ]
    },
    {
      "nameRegion": "3",
      "typeRegion": "PENALTY_REGION",
      "coordenates": [
        {
          "x": 450.49,
          "y": 216.16
        },
        {
          "x": 394.84,
          "y": 170.11
        },
        {
          "x": 348.79,
          "y": 225.75
        },
        {
          "x": 404.44,
          "y": 271.8
        }
      ]
    },
    {
      "nameRegion": "4",
      "typeRegion": "PENALTY_REGION",
      "coordenates": [
        {
          "x": 337.19,
          "y": -470.72
        },
        {
          "x": 220.7,
          "y": -631.11
        },
        {
          "x": 60.3,
          "y": -514.62
        },
        {
          "x": 176.79,
          "y": -354.23
        }
      ]
    },
    {
      "nameRegion": "5",
      "typeRegion": "PENALTY_REGION",
      "coordenates": [
        {
          "x": 421.58,
          "y": -559.57
        },
        {
          "x": 373.93,
          "y": -419.61
        },
        {
          "x": 513.88,
          "y": -371.96
        },
        {
          "x": 561.54,
          "y": -511.91
        }
      ]
    },
    {
      "nameRegion": "6",
      "typeRegion": "PENALTY_REGION",
      "coordenates": [
        {
          "x": 136.9,
          "y": -152.93
        },
        {
          "x": 65.65,
          "y": -205.72
        },
        {
          "x": 12.86,
          "y": -134.47
        },
        {
          "x": 84.1,
          "y": -81.68
        }
      ]
    },
    {
      "nameRegion": "7",
      "typeRegion": "PENALTY_REGION",
      "coordenates": [
        {
          "x": 70.28,
          "y": 24.8
        },
        {
          "x": 11.34,
          "y": 67.24
        },
        {
          "x": 53.79,
          "y": 126.17
        },
        {
          "x": 112.72,
          "y": 83.73
        }
      ]
    },
    {
      "nameRegion": "8",
      "typeRegion": "PENALTY_REGION",
      "coordenates": [
        {
          "x": -123.68,
          "y": 74.94
        },
        {
          "x": -243.79,
          "y": 140.29
        },
        {
          "x": -178.45,
          "y": 260.4
        },
        {
          "x": -58.33,
          "y": 195.05
        }
      ]
    },
    {
      "nameRegion": "9",
      "typeRegion": "PENALTY_REGION",
      "coordenates": [
        {
          "x": 49.55,
          "y": -460.98
        },
        {
          "x": 25.64,
          "y": -557.8
        },
        {
          "x": -71.16,
          "y": -533.89
        },
        {
          "x": -47.26,
          "y": -437.08
        }
      ]
    },
    {
      "nameRegion": "0",
      "typeRegion": "BONUS_REGION",
      "coordenates": [
        {
          "x": -108.73,
          "y": -27.02
        },
        {
          "x": -190.41,
          "y": -137.01
        },
        {
          "x": -300.4,
          "y": -55.33
        },
        {
          "x": -218.72,
          "y": 54.65
        }
      ]
    },
    {
      "nameRegion": "1",
      "typeRegion": "BONUS_REGION",
      "coordenates": [
        {
          "x": 444.22,
          "y": -376.65
        },
        {
          "x": 411.56,
          "y": -299.22
        },
        {
          "x": 488.99,
          "y": -266.55
        },
        {
          "x": 521.65,
          "y": -343.98
        }
      ]
    },
    {
      "nameRegion": "2",
      "typeRegion": "BONUS_REGION",
      "coordenates": [
        {
          "x": 107.12,
          "y": -377.29
        },
        {
          "x": 21.72,
          "y": -397.78
        },
        {
          "x": 1.23,
          "y": -312.38
        },
        {
          "x": 86.63,
          "y": -291.9
        }
      ]
    },
    {
      "nameRegion": "3",
      "typeRegion": "BONUS_REGION",
      "coordenates": [
        {
          "x": -34.95,
          "y": 303.04
        },
        {
          "x": -64.48,
          "y": 291.86
        },
        {
          "x": -75.66,
          "y": 321.39
        },
        {
          "x": -46.13,
          "y": 332.57
        }
      ]
    },
    {
      "nameRegion": "4",
      "typeRegion": "BONUS_REGION",
      "coordenates": [
        {
          "x": -463.36,
          "y": -472.5
        },
        {
          "x": -584.58,
          "y": -376.21
        },
        {
          "x": -488.29,
          "y": -254.99
        },
        {
          "x": -367.07,
          "y": -351.28
        }
      ]
    },
    {
      "nameRegion": "5",
      "typeRegion": "BONUS_REGION",
      "coordenates": [
        {
          "x": 85.58,
          "y": -42.34
        },
        {
          "x": -0.78,
          "y": -150.66
        },
        {
          "x": -109.1,
          "y": -64.29
        },
        {
          "x": -22.73,
          "y": 44.02
        }
      ]
    }
  ]
}
