{
  "regions": [
    {
      "nameRegion": "0",
      "typeRegion": "NFZ_REGION",
      "coordenates": [
        {
          "x": -1.05,
          "y": -5.37
        },
        {
          "x": -1.83,
          "y": -5.43
        },
        {
          "x": -1.9,
          "y": -4.66
        },
        {
          "x": -1.12,
          "y": -4.59
        }
      ]
    },
    {
      "nameRegion": "1",
      "typeRegion": "NFZ_REGION",
      "coordenates": [
        {
          "x": -3.27,
          "y": -2.05
        },
        {
          "x": -3.66,
          "y": -4.0
        },
        {
          "x": -5.61,
          "y": -3.61
        },
        {
          "x": -5.22,
          "y": -1.66
        }
      ]
    },
    {
      "nameRegion": "2",
      "typeRegion": "NFZ_REGION",
      "coordenates": [
        {
          "x": -2.92,
          "y": -6.45
        },
        {
          "x": -3.25,
          "y": -5.13
        },
        {
          "x": -1.93,
          "y": -4.8
        },
        {
          "x": -1.6,
          "y": -6.12
        }
      ]
    },
    {
      "nameRegion": "3",
      "typeRegion": "NFZ_REGION",
      "coordenates": [
        {
          "x": 2.22,
          "y": -5.77
        },
        {
          "x": 1.68,
          "y": -4.56
        },
        {
          "x": 2.89,
          "y": -4.01
        },
        {
          "x": 3.44,
          "y": -5.23
        }
      ]
    },
    {
      "nameRegion": "4",
      "typeRegion": "NFZ_REGION",
      "coordenates": [
        {
          "x": 4.2,
          "y": -4.91
        },
        {
          "x": 3.03,
          "y": -5.08
        },
        {
          "x": 2.86,
          "y": -3.91
        },
        {
          "x": 4.04,
          "y": -3.74
        }
      ]
    },
    {
      "nameRegion": "5",
      "typeRegion": "NFZ_REGION",
      "coordenates": [
        {
          "x": 3.14,
          "y": -2.85
        },
        {
          "x": 2.04,
          "y": -1.69
        },
        {
          "x": 3.21,
          "y": -0.59
        },
        {
          "x": 4.3,
          "y": -1.76
        }
      ]
    },
    {
      "nameRegion": "6",
      "typeRegion": "NFZ_REGION",
      "coordenates": [
        {
          "x": 4.69,
          "y": -10.62
        },
        {
          "x": 3.64,
          "y": -10.02
        },
        {
          "x": 4.24,
          "y": -8.97
        },
        {
          "x": 5.29,
          "y": -9.57
        }
      ]
    },
    {
      "nameRegion": "7",
      "typeRegion": "NFZ_REGION",
      "coordenates": [
        {
          "x": -2.45,
          "y": -8.14
        },
        {
          "x": -2.85,
          "y": -9.02
        },
        {
          "x": -3.74,
          "y": -8.63
        },
        {
          "x": -3.34,
          "y": -7.74
        }
      ]
    },
    {
      "nameRegion": "8",
      "typeRegion": "NFZ_REGION",
      "coordenates": [
        {
          "x": 0.08,
          "y": -4.86
        },
        {
          "x": -0.57,
          "y": -5.46
        },
        {
          "x": -1.17,
          "y": -4.8
        },
        {
          "x": -0.51,
          "y": -4.2
        }
      ]
    },
    {
      "nameRegion": "9",
      "typeRegion": "NFZ_REGION",
      "coordenates": [
        {
          "x": 1.57,
          "y": -7.19
        },
        {
          "x": 0.86,
          "y": -7.21
        },
        {
          "x": 0.84,
          "y": -6.5
        },
        {
          "x": 1.55,
          "y": -6.48
        }
      ]
    },
    {
      "nameRegion": "10",
      "typeRegion": "NFZ_REGION",
      "coordenates": [
        {
          "x": 0.64,
          "y": -6.68
        },
        {
          "x": 0.5,
          "y": -7.54
        },
        {
          "x": -0.35,
          "y": -7.4
        },
        {
          "x": -0.21,
          "y": -6.54
        }
      ]
    },
    {
      "nameRegion": "11",
      "typeRegion": "NFZ_REGION",
      "coordenates": [
        {
          "x": 4.82,
          "y": -5.42
        },
        {
          "x": 3.99,
          "y": -6.34
        },
        {
          "x": 3.07,
          "y": -5.5
        },
        {
          "x": 3.91,
          "y": -4.58
        }
      ]
    },
    {
      "nameRegion": "12",
      "typeRegion": "NFZ_REGION",
      "coordenates": [
        {
          "x": 3.39,
          "y": -5.15
        },
        {
          "x": 2.15,
          "y": -6.02
        },
        {
          "x": 1.29,
          "y": -4.78
        },
        {
          "x": 2.53,
          "y": -3.92
        }
      ]
    },
    {
      "nameRegion": "13",
      "typeRegion": "NFZ_REGION",
      "coordenates": [
        {
          "x": 5.51,
          "y": -7.65
        },
        {
          "x": 4.81,
          "y": -8.14
        },
        {
          "x": 4.32,
          "y": -7.45
        },
        {
          "x": 5.01,
          "y": -6.95
        }
      ]
    },
    {
      "nameRegion": "14",
      "typeRegion": "NFZ_REGION",
      "coordenates": [
        {
          "x": -0.64,
          "y": -3.87
        },
        {
          "x": -0.87,
          "y": -4.35
        },
        {
          "x": -1.35,
          "y": -4.12
        },
        {
          "x": -1.12,
          "y": -3.65
        }
      ]
    },
    {
      "nameRegion": "15",
      "typeRegion": "NFZ_REGION",
      "coordenates": [
        {
          "x": 3.59,
          "y": -5.72
        },
        {
          "x": 3.39,
          "y": -7.2
        },
        {
          "x": 1.91,
          "y": -6.99
        },
        {
          "x": 2.12,
          "y": -5.52
        }
      ]
    },
    {
      "nameRegion": "16",
      "typeRegion": "NFZ_REGION",
      "coordenates": [
        {
          "x": 3.44,
          "y": -7.8
        },
        {
          "x": 2.52,
          "y": -6.35
        },
        {
          "x": 3.97,
          "y": -5.43
        },
        {
          "x": 4.89,
          "y": -6.87
        }
      ]
    },
    {
      "nameRegion": "17",
      "typeRegion": "NFZ_REGION",
      "coordenates": [
        {
          "x": -1.68,
          "y": -4.16
        },
        {
          "x": -2.74,
          "y": -3.53
        },
        {
          "x": -2.11,
          "y": -2.47
        },
        {
          "x": -1.05,
          "y": -3.1
        }
      ]
    },
    {
      "nameRegion": "18",
      "typeRegion": "NFZ_REGION",
      "coordenates": [
        {
          "x": -3.99,
          "y": -8.01
        },
        {
          "x": -5.09,
          "y": -7.78
        },
        {
          "x": -4.86,
          "y": -6.68
        },
        {
          "x": -3.76,
          "y": -6.91
        }
      ]
    },
    {
      "nameRegion": "19",
      "typeRegion": "NFZ_REGION",
      "coordenates": [
        {
          "x": 4.97,
          "y": -1.96
        },
        {
          "x": 4.31,
          "y": -2.4
        },
        {
          "x": 3.86,
          "y": -1.74
        },
        {
          "x": 4.53,
          "y": -1.3
        }
      ]
    }
  ]
}
